{"nm":"Icon - Routine Visit","ddd":0,"h":80,"w":80,"meta":{"g":"LottieFiles Figma v55"},"layers":[{"ty":4,"nm":"Ellipse 1","sr":1,"st":0,"op":241.06,"ip":0,"hd":false,"ddd":0,"bm":0,"hasMask":false,"td":1,"ao":0,"ks":{"a":{"a":1,"k":[{"o":{"x":0.65,"y":0},"i":{"x":0.35,"y":0},"s":[40,40],"t":0},{"o":{"x":0.65,"y":0},"i":{"x":0.35,"y":0},"s":[40,40],"t":24},{"o":{"x":0.65,"y":0},"i":{"x":0.35,"y":0},"s":[40,40],"t":48},{"o":{"x":0.65,"y":0},"i":{"x":0.35,"y":0},"s":[40,40],"t":72},{"o":{"x":0.65,"y":0},"i":{"x":0.35,"y":0},"s":[40,40],"t":216},{"s":[40,40],"t":240}]},"s":{"a":1,"k":[{"o":{"x":0.65,"y":0},"i":{"x":0.35,"y":0},"s":[100,100],"t":0},{"o":{"x":0.65,"y":0},"i":{"x":0.35,"y":0},"s":[100,100],"t":24},{"o":{"x":0.65,"y":0},"i":{"x":0.35,"y":0},"s":[100,100],"t":48},{"o":{"x":0.65,"y":0},"i":{"x":0.35,"y":0},"s":[100,100],"t":72},{"o":{"x":0.65,"y":0},"i":{"x":0.35,"y":0},"s":[100,100],"t":216},{"s":[100,100],"t":240}]},"sk":{"a":0,"k":0},"p":{"a":1,"k":[{"o":{"x":0.65,"y":0},"i":{"x":0.35,"y":0},"s":[40,40],"t":0},{"o":{"x":0.65,"y":0},"i":{"x":0.35,"y":0},"s":[40,40],"t":24},{"o":{"x":0.65,"y":0},"i":{"x":0.35,"y":0},"s":[40,40],"t":48},{"o":{"x":0.65,"y":0},"i":{"x":0.35,"y":0},"s":[40,40],"t":72},{"o":{"x":0.65,"y":0},"i":{"x":0.35,"y":0},"s":[40,40],"t":216},{"s":[40,40],"t":240}]},"r":{"a":1,"k":[{"o":{"x":0.65,"y":0},"i":{"x":0.35,"y":0},"s":[0],"t":0},{"o":{"x":0.65,"y":0},"i":{"x":0.35,"y":0},"s":[0],"t":24},{"o":{"x":0.65,"y":0},"i":{"x":0.35,"y":0},"s":[0],"t":48},{"o":{"x":0.65,"y":0},"i":{"x":0.35,"y":0},"s":[0],"t":72},{"o":{"x":0.65,"y":0},"i":{"x":0.35,"y":0},"s":[0],"t":216},{"s":[0],"t":240}]},"sa":{"a":0,"k":0},"o":{"a":1,"k":[{"o":{"x":0.65,"y":0},"i":{"x":0.35,"y":0},"s":[100],"t":0},{"o":{"x":0.65,"y":0},"i":{"x":0.35,"y":0},"s":[100],"t":24},{"o":{"x":0.65,"y":0},"i":{"x":0.35,"y":0},"s":[100],"t":48},{"o":{"x":0.65,"y":0},"i":{"x":0.35,"y":0},"s":[100],"t":72},{"o":{"x":0.65,"y":0},"i":{"x":0.35,"y":0},"s":[100],"t":216},{"s":[100],"t":240}]}},"shapes":[{"ty":"sh","bm":0,"hd":false,"nm":"","d":1,"ks":{"a":1,"k":[{"o":{"x":0.65,"y":0},"i":{"x":0.35,"y":0},"s":[{"c":true,"i":[[0,0],[22.09,0],[0,22.09],[-22.09,0],[0,-22.09]],"o":[[0,22.09],[-22.09,0],[0,-22.09],[22.09,0],[0,0]],"v":[[80,40],[40,80],[0,40],[40,0],[80,40]]}],"t":0},{"o":{"x":0.65,"y":0},"i":{"x":0.35,"y":0},"s":[{"c":true,"i":[[0,0],[22.09,0],[0,22.09],[-22.09,0],[0,-22.09]],"o":[[0,22.09],[-22.09,0],[0,-22.09],[22.09,0],[0,0]],"v":[[80,40],[40,80],[0,40],[40,0],[80,40]]}],"t":24},{"o":{"x":0.65,"y":0},"i":{"x":0.35,"y":0},"s":[{"c":true,"i":[[0,0],[22.09,0],[0,22.09],[-22.09,0],[0,-22.09]],"o":[[0,22.09],[-22.09,0],[0,-22.09],[22.09,0],[0,0]],"v":[[80,40],[40,80],[0,40],[40,0],[80,40]]}],"t":48},{"o":{"x":0.65,"y":0},"i":{"x":0.35,"y":0},"s":[{"c":true,"i":[[0,0],[22.09,0],[0,22.09],[-22.09,0],[0,-22.09]],"o":[[0,22.09],[-22.09,0],[0,-22.09],[22.09,0],[0,0]],"v":[[80,40],[40,80],[0,40],[40,0],[80,40]]}],"t":72},{"o":{"x":0.65,"y":0},"i":{"x":0.35,"y":0},"s":[{"c":true,"i":[[0,0],[22.09,0],[0,22.09],[-22.09,0],[0,-22.09]],"o":[[0,22.09],[-22.09,0],[0,-22.09],[22.09,0],[0,0]],"v":[[80,40],[40,80],[0,40],[40,0],[80,40]]}],"t":216},{"s":[{"c":true,"i":[[0,0],[22.09,0],[0,22.09],[-22.09,0],[0,-22.09]],"o":[[0,22.09],[-22.09,0],[0,-22.09],[22.09,0],[0,0]],"v":[[80,40],[40,80],[0,40],[40,0],[80,40]]}],"t":240}]}},{"ty":"fl","bm":0,"hd":false,"nm":"","c":{"a":1,"k":[{"o":{"x":0.65,"y":0},"i":{"x":0.35,"y":0},"s":[0.7608,0.8392,0.6392],"t":0},{"o":{"x":0.65,"y":0},"i":{"x":0.35,"y":0},"s":[0.7608,0.8392,0.6392],"t":24},{"o":{"x":0.65,"y":0},"i":{"x":0.35,"y":0},"s":[0.7608,0.8392,0.6392],"t":48},{"o":{"x":0.65,"y":0},"i":{"x":0.35,"y":0},"s":[0.7608,0.8392,0.6392],"t":72},{"o":{"x":0.65,"y":0},"i":{"x":0.35,"y":0},"s":[0.7608,0.8392,0.6392],"t":216},{"s":[0.7608,0.8392,0.6392],"t":240}]},"r":1,"o":{"a":1,"k":[{"o":{"x":0.65,"y":0},"i":{"x":0.35,"y":0},"s":[100],"t":0},{"o":{"x":0.65,"y":0},"i":{"x":0.35,"y":0},"s":[100],"t":24},{"o":{"x":0.65,"y":0},"i":{"x":0.35,"y":0},"s":[100],"t":48},{"o":{"x":0.65,"y":0},"i":{"x":0.35,"y":0},"s":[100],"t":72},{"o":{"x":0.65,"y":0},"i":{"x":0.35,"y":0},"s":[100],"t":216},{"s":[100],"t":240}]}}],"ind":1},{"ty":4,"nm":"Clip","sr":1,"st":0,"op":241.06,"ip":0,"hd":false,"ddd":0,"bm":0,"tt":1,"hasMask":false,"ao":0,"ks":{"a":{"a":1,"k":[{"o":{"x":0.65,"y":0},"i":{"x":0.35,"y":0},"s":[4.57,2.38],"t":0},{"o":{"x":0.65,"y":0},"i":{"x":0.35,"y":0},"s":[4.57,2.38],"t":24},{"o":{"x":0.65,"y":0},"i":{"x":0.35,"y":0},"s":[4.57,2.38],"t":48},{"o":{"x":0.65,"y":0},"i":{"x":0.35,"y":0},"s":[8.57,4.76],"t":72},{"o":{"x":0.65,"y":0},"i":{"x":0.35,"y":0},"s":[8.57,4.76],"t":216},{"s":[8.57,4.76],"t":240}]},"s":{"a":1,"k":[{"o":{"x":0.65,"y":0},"i":{"x":0.35,"y":0},"s":[100,100],"t":0},{"o":{"x":0.65,"y":0},"i":{"x":0.35,"y":0},"s":[100,100],"t":24},{"o":{"x":0.65,"y":0},"i":{"x":0.35,"y":0},"s":[100,100],"t":48},{"o":{"x":0.65,"y":0},"i":{"x":0.35,"y":0},"s":[100,100],"t":72},{"o":{"x":0.65,"y":0},"i":{"x":0.35,"y":0},"s":[100,100],"t":216},{"s":[100,100],"t":240}]},"sk":{"a":0,"k":0},"p":{"a":1,"k":[{"o":{"x":0.65,"y":0},"i":{"x":0.35,"y":0},"s":[84.75,18.32],"t":0},{"o":{"x":0.65,"y":0},"i":{"x":0.35,"y":0},"s":[84.75,18.32],"t":24},{"o":{"x":0.65,"y":0},"i":{"x":0.35,"y":0},"s":[36.75,18.32],"t":48},{"o":{"x":0.65,"y":0},"i":{"x":0.35,"y":0},"s":[40.75,21.7],"t":72},{"o":{"x":0.65,"y":0},"i":{"x":0.35,"y":0},"s":[40.75,21.7],"t":216},{"s":[40.75,21.7],"t":240}]},"r":{"a":1,"k":[{"o":{"x":0.65,"y":0},"i":{"x":0.35,"y":0},"s":[0],"t":0},{"o":{"x":0.65,"y":0},"i":{"x":0.35,"y":0},"s":[0],"t":24},{"o":{"x":0.65,"y":0},"i":{"x":0.35,"y":0},"s":[0],"t":48},{"o":{"x":0.65,"y":0},"i":{"x":0.35,"y":0},"s":[0],"t":72},{"o":{"x":0.65,"y":0},"i":{"x":0.35,"y":0},"s":[0],"t":216},{"s":[0],"t":240}]},"sa":{"a":0,"k":0},"o":{"a":1,"k":[{"o":{"x":0.65,"y":0},"i":{"x":0.35,"y":0},"s":[100],"t":0},{"o":{"x":0.65,"y":0},"i":{"x":0.35,"y":0},"s":[100],"t":24},{"o":{"x":0.65,"y":0},"i":{"x":0.35,"y":0},"s":[100],"t":48},{"o":{"x":0.65,"y":0},"i":{"x":0.35,"y":0},"s":[100],"t":72},{"o":{"x":0.65,"y":0},"i":{"x":0.35,"y":0},"s":[100],"t":216},{"s":[100],"t":240}]}},"shapes":[{"ty":"sh","bm":0,"hd":false,"nm":"","d":1,"ks":{"a":1,"k":[{"o":{"x":0.65,"y":0},"i":{"x":0.35,"y":0},"s":[{"c":true,"i":[[0,0],[-0.5266083189821353,0],[0,0],[0,-0.4314705977814652],[0,0],[0.5266083189821353,0],[0,0],[0,0.4314705977814652],[0,0]],"o":[[0,-0.4314705977814652],[0,0],[0.5266083189821353,0],[0,0],[0,0.4314705977814652],[0,0],[-0.5266083189821353,0],[0,0],[0,0]],"v":[[0,0.7807563197950321],[0.9529102914914829,0],[6.687089764852512,0],[7.640000056343996,0.7807563197950321],[7.640000056343996,2.4792437523315938],[6.687089764852512,3.260000072126626],[0.9529102914914829,3.260000072126626],[0,2.4792437523315938],[0,0.7807563197950321]]}],"t":0},{"o":{"x":0.65,"y":0},"i":{"x":0.35,"y":0},"s":[{"c":true,"i":[[0,0],[-0.5266083189821353,0],[0,0],[0,-0.4314705977814652],[0,0],[0.5266083189821353,0],[0,0],[0,0.4314705977814652],[0,0]],"o":[[0,-0.4314705977814652],[0,0],[0.5266083189821353,0],[0,0],[0,0.4314705977814652],[0,0],[-0.5266083189821353,0],[0,0],[0,0]],"v":[[0,0.7807563197950321],[0.9529102914914829,0],[6.687089764852512,0],[7.640000056343996,0.7807563197950321],[7.640000056343996,2.4792437523315938],[6.687089764852512,3.260000072126626],[0.9529102914914829,3.260000072126626],[0,2.4792437523315938],[0,0.7807563197950321]]}],"t":24},{"o":{"x":0.65,"y":0},"i":{"x":0.35,"y":0},"s":[{"c":true,"i":[[0,0],[-0.5266083189821353,0],[0,0],[0,-0.4314705977814652],[0,0],[0.5266083189821353,0],[0,0],[0,0.4314705977814652],[0,0]],"o":[[0,-0.4314705977814652],[0,0],[0.5266083189821353,0],[0,0],[0,0.4314705977814652],[0,0],[-0.5266083189821353,0],[0,0],[0,0]],"v":[[0,0.7807563197950321],[0.9529102914914829,0],[6.687089764852512,0],[7.640000056343996,0.7807563197950321],[7.640000056343996,2.4792437523315938],[6.687089764852512,3.260000072126626],[0.9529102914914829,3.260000072126626],[0,2.4792437523315938],[0,0.7807563197950321]]}],"t":48},{"o":{"x":0.65,"y":0},"i":{"x":0.35,"y":0},"s":[{"c":true,"i":[[0,0],[-0.5748749921143044,0],[0,0],[0,-0.5307750189256633],[0,0],[0.5748749921143044,0],[0,0],[0,0.5307750189256633],[0,0]],"o":[[0,-0.5307750189256633],[0,0],[0.5748749921143044,0],[0,0],[0,0.5307750189256633],[0,0],[-0.5748749921143044,0],[0,0],[0,0]],"v":[[0,0.9604500342464382],[1.040249985730646,0],[14.599999799728366,0],[15.640249785459012,0.9604500342464382],[15.640249785459012,7.060150251741362],[14.599999799728366,8.020600285987799],[1.040249985730646,8.020600285987799],[0,7.060150251741362],[0,0.9604500342464382]]}],"t":72},{"o":{"x":0.65,"y":0},"i":{"x":0.35,"y":0},"s":[{"c":true,"i":[[0,0],[-0.5748749921143044,0],[0,0],[0,-0.5307750189256633],[0,0],[0.5748749921143044,0],[0,0],[0,0.5307750189256633],[0,0]],"o":[[0,-0.5307750189256633],[0,0],[0.5748749921143044,0],[0,0],[0,0.5307750189256633],[0,0],[-0.5748749921143044,0],[0,0],[0,0]],"v":[[0,0.9604500342464382],[1.040249985730646,0],[14.599999799728366,0],[15.640249785459012,0.9604500342464382],[15.640249785459012,7.060150251741362],[14.599999799728366,8.020600285987799],[1.040249985730646,8.020600285987799],[0,7.060150251741362],[0,0.9604500342464382]]}],"t":216},{"s":[{"c":true,"i":[[0,0],[-0.5748749921143044,0],[0,0],[0,-0.5307750189256633],[0,0],[0.5748749921143044,0],[0,0],[0,0.5307750189256633],[0,0]],"o":[[0,-0.5307750189256633],[0,0],[0.5748749921143044,0],[0,0],[0,0.5307750189256633],[0,0],[-0.5748749921143044,0],[0,0],[0,0]],"v":[[0,0.9604500342464382],[1.040249985730646,0],[14.599999799728366,0],[15.640249785459012,0.9604500342464382],[15.640249785459012,7.060150251741362],[14.599999799728366,8.020600285987799],[1.040249985730646,8.020600285987799],[0,7.060150251741362],[0,0.9604500342464382]]}],"t":240}]}},{"ty":"st","bm":0,"hd":false,"nm":"","lc":1,"lj":1,"ml":4,"o":{"a":1,"k":[{"o":{"x":0.65,"y":0},"i":{"x":0.35,"y":0},"s":[100],"t":0},{"o":{"x":0.65,"y":0},"i":{"x":0.35,"y":0},"s":[100],"t":24},{"o":{"x":0.65,"y":0},"i":{"x":0.35,"y":0},"s":[100],"t":48},{"o":{"x":0.65,"y":0},"i":{"x":0.35,"y":0},"s":[100],"t":72},{"o":{"x":0.65,"y":0},"i":{"x":0.35,"y":0},"s":[100],"t":216},{"s":[100],"t":240}]},"w":{"a":1,"k":[{"o":{"x":0.65,"y":0},"i":{"x":0.35,"y":0},"s":[1.5],"t":0},{"o":{"x":0.65,"y":0},"i":{"x":0.35,"y":0},"s":[1.5],"t":24},{"o":{"x":0.65,"y":0},"i":{"x":0.35,"y":0},"s":[1.5],"t":48},{"o":{"x":0.65,"y":0},"i":{"x":0.35,"y":0},"s":[1.5],"t":72},{"o":{"x":0.65,"y":0},"i":{"x":0.35,"y":0},"s":[1.5],"t":216},{"s":[1.5],"t":240}]},"c":{"a":1,"k":[{"o":{"x":0.65,"y":0},"i":{"x":0.35,"y":0},"s":[0,0.3294,0.3137],"t":0},{"o":{"x":0.65,"y":0},"i":{"x":0.35,"y":0},"s":[0,0.3294,0.3137],"t":24},{"o":{"x":0.65,"y":0},"i":{"x":0.35,"y":0},"s":[0,0.3294,0.3137],"t":48},{"o":{"x":0.65,"y":0},"i":{"x":0.35,"y":0},"s":[0,0.3294,0.3137],"t":72},{"o":{"x":0.65,"y":0},"i":{"x":0.35,"y":0},"s":[0,0.3294,0.3137],"t":216},{"s":[0,0.3294,0.3137],"t":240}]}},{"ty":"fl","bm":0,"hd":false,"nm":"","c":{"a":1,"k":[{"o":{"x":0.65,"y":0},"i":{"x":0.35,"y":0},"s":[1,1,1],"t":0},{"o":{"x":0.65,"y":0},"i":{"x":0.35,"y":0},"s":[1,1,1],"t":24},{"o":{"x":0.65,"y":0},"i":{"x":0.35,"y":0},"s":[1,1,1],"t":48},{"o":{"x":0.65,"y":0},"i":{"x":0.35,"y":0},"s":[1,1,1],"t":72},{"o":{"x":0.65,"y":0},"i":{"x":0.35,"y":0},"s":[1,1,1],"t":216},{"s":[1,1,1],"t":240}]},"r":1,"o":{"a":1,"k":[{"o":{"x":0.65,"y":0},"i":{"x":0.35,"y":0},"s":[100],"t":0},{"o":{"x":0.65,"y":0},"i":{"x":0.35,"y":0},"s":[100],"t":24},{"o":{"x":0.65,"y":0},"i":{"x":0.35,"y":0},"s":[100],"t":48},{"o":{"x":0.65,"y":0},"i":{"x":0.35,"y":0},"s":[100],"t":72},{"o":{"x":0.65,"y":0},"i":{"x":0.35,"y":0},"s":[100],"t":216},{"s":[100],"t":240}]}}],"ind":2},{"ty":4,"nm":"Ellipse 1","sr":1,"st":0,"op":241.06,"ip":0,"hd":false,"ddd":0,"bm":0,"hasMask":false,"td":1,"ao":0,"ks":{"a":{"a":1,"k":[{"o":{"x":0.65,"y":0},"i":{"x":0.35,"y":0},"s":[40,40],"t":0},{"o":{"x":0.65,"y":0},"i":{"x":0.35,"y":0},"s":[40,40],"t":24},{"o":{"x":0.65,"y":0},"i":{"x":0.35,"y":0},"s":[40,40],"t":48},{"o":{"x":0.65,"y":0},"i":{"x":0.35,"y":0},"s":[40,40],"t":72},{"o":{"x":0.65,"y":0},"i":{"x":0.35,"y":0},"s":[40,40],"t":216},{"s":[40,40],"t":240}]},"s":{"a":1,"k":[{"o":{"x":0.65,"y":0},"i":{"x":0.35,"y":0},"s":[100,100],"t":0},{"o":{"x":0.65,"y":0},"i":{"x":0.35,"y":0},"s":[100,100],"t":24},{"o":{"x":0.65,"y":0},"i":{"x":0.35,"y":0},"s":[100,100],"t":48},{"o":{"x":0.65,"y":0},"i":{"x":0.35,"y":0},"s":[100,100],"t":72},{"o":{"x":0.65,"y":0},"i":{"x":0.35,"y":0},"s":[100,100],"t":216},{"s":[100,100],"t":240}]},"sk":{"a":0,"k":0},"p":{"a":1,"k":[{"o":{"x":0.65,"y":0},"i":{"x":0.35,"y":0},"s":[40,40],"t":0},{"o":{"x":0.65,"y":0},"i":{"x":0.35,"y":0},"s":[40,40],"t":24},{"o":{"x":0.65,"y":0},"i":{"x":0.35,"y":0},"s":[40,40],"t":48},{"o":{"x":0.65,"y":0},"i":{"x":0.35,"y":0},"s":[40,40],"t":72},{"o":{"x":0.65,"y":0},"i":{"x":0.35,"y":0},"s":[40,40],"t":216},{"s":[40,40],"t":240}]},"r":{"a":1,"k":[{"o":{"x":0.65,"y":0},"i":{"x":0.35,"y":0},"s":[0],"t":0},{"o":{"x":0.65,"y":0},"i":{"x":0.35,"y":0},"s":[0],"t":24},{"o":{"x":0.65,"y":0},"i":{"x":0.35,"y":0},"s":[0],"t":48},{"o":{"x":0.65,"y":0},"i":{"x":0.35,"y":0},"s":[0],"t":72},{"o":{"x":0.65,"y":0},"i":{"x":0.35,"y":0},"s":[0],"t":216},{"s":[0],"t":240}]},"sa":{"a":0,"k":0},"o":{"a":1,"k":[{"o":{"x":0.65,"y":0},"i":{"x":0.35,"y":0},"s":[100],"t":0},{"o":{"x":0.65,"y":0},"i":{"x":0.35,"y":0},"s":[100],"t":24},{"o":{"x":0.65,"y":0},"i":{"x":0.35,"y":0},"s":[100],"t":48},{"o":{"x":0.65,"y":0},"i":{"x":0.35,"y":0},"s":[100],"t":72},{"o":{"x":0.65,"y":0},"i":{"x":0.35,"y":0},"s":[100],"t":216},{"s":[100],"t":240}]}},"shapes":[{"ty":"sh","bm":0,"hd":false,"nm":"","d":1,"ks":{"a":1,"k":[{"o":{"x":0.65,"y":0},"i":{"x":0.35,"y":0},"s":[{"c":true,"i":[[0,0],[22.09,0],[0,22.09],[-22.09,0],[0,-22.09]],"o":[[0,22.09],[-22.09,0],[0,-22.09],[22.09,0],[0,0]],"v":[[80,40],[40,80],[0,40],[40,0],[80,40]]}],"t":0},{"o":{"x":0.65,"y":0},"i":{"x":0.35,"y":0},"s":[{"c":true,"i":[[0,0],[22.09,0],[0,22.09],[-22.09,0],[0,-22.09]],"o":[[0,22.09],[-22.09,0],[0,-22.09],[22.09,0],[0,0]],"v":[[80,40],[40,80],[0,40],[40,0],[80,40]]}],"t":24},{"o":{"x":0.65,"y":0},"i":{"x":0.35,"y":0},"s":[{"c":true,"i":[[0,0],[22.09,0],[0,22.09],[-22.09,0],[0,-22.09]],"o":[[0,22.09],[-22.09,0],[0,-22.09],[22.09,0],[0,0]],"v":[[80,40],[40,80],[0,40],[40,0],[80,40]]}],"t":48},{"o":{"x":0.65,"y":0},"i":{"x":0.35,"y":0},"s":[{"c":true,"i":[[0,0],[22.09,0],[0,22.09],[-22.09,0],[0,-22.09]],"o":[[0,22.09],[-22.09,0],[0,-22.09],[22.09,0],[0,0]],"v":[[80,40],[40,80],[0,40],[40,0],[80,40]]}],"t":72},{"o":{"x":0.65,"y":0},"i":{"x":0.35,"y":0},"s":[{"c":true,"i":[[0,0],[22.09,0],[0,22.09],[-22.09,0],[0,-22.09]],"o":[[0,22.09],[-22.09,0],[0,-22.09],[22.09,0],[0,0]],"v":[[80,40],[40,80],[0,40],[40,0],[80,40]]}],"t":216},{"s":[{"c":true,"i":[[0,0],[22.09,0],[0,22.09],[-22.09,0],[0,-22.09]],"o":[[0,22.09],[-22.09,0],[0,-22.09],[22.09,0],[0,0]],"v":[[80,40],[40,80],[0,40],[40,0],[80,40]]}],"t":240}]}},{"ty":"fl","bm":0,"hd":false,"nm":"","c":{"a":1,"k":[{"o":{"x":0.65,"y":0},"i":{"x":0.35,"y":0},"s":[0.7608,0.8392,0.6392],"t":0},{"o":{"x":0.65,"y":0},"i":{"x":0.35,"y":0},"s":[0.7608,0.8392,0.6392],"t":24},{"o":{"x":0.65,"y":0},"i":{"x":0.35,"y":0},"s":[0.7608,0.8392,0.6392],"t":48},{"o":{"x":0.65,"y":0},"i":{"x":0.35,"y":0},"s":[0.7608,0.8392,0.6392],"t":72},{"o":{"x":0.65,"y":0},"i":{"x":0.35,"y":0},"s":[0.7608,0.8392,0.6392],"t":216},{"s":[0.7608,0.8392,0.6392],"t":240}]},"r":1,"o":{"a":1,"k":[{"o":{"x":0.65,"y":0},"i":{"x":0.35,"y":0},"s":[100],"t":0},{"o":{"x":0.65,"y":0},"i":{"x":0.35,"y":0},"s":[100],"t":24},{"o":{"x":0.65,"y":0},"i":{"x":0.35,"y":0},"s":[100],"t":48},{"o":{"x":0.65,"y":0},"i":{"x":0.35,"y":0},"s":[100],"t":72},{"o":{"x":0.65,"y":0},"i":{"x":0.35,"y":0},"s":[100],"t":216},{"s":[100],"t":240}]}}],"ind":3},{"ty":4,"nm":"Line 2","sr":1,"st":0,"op":241.06,"ip":0,"hd":false,"ddd":0,"bm":0,"tt":1,"hasMask":false,"ao":0,"ks":{"a":{"a":1,"k":[{"o":{"x":0.65,"y":0},"i":{"x":0.35,"y":0},"s":[0.13,0],"t":0},{"o":{"x":0.65,"y":0},"i":{"x":0.35,"y":0},"s":[0.13,0],"t":24},{"o":{"x":0.65,"y":0},"i":{"x":0.35,"y":0},"s":[1.88,0],"t":48},{"o":{"x":0.65,"y":0},"i":{"x":0.35,"y":0},"s":[5.88,0],"t":72},{"o":{"x":0.65,"y":0},"i":{"x":0.35,"y":0},"s":[5.88,0],"t":216},{"s":[5.88,0],"t":240}]},"s":{"a":1,"k":[{"o":{"x":0.65,"y":0},"i":{"x":0.35,"y":0},"s":[100,100],"t":0},{"o":{"x":0.65,"y":0},"i":{"x":0.35,"y":0},"s":[100,100],"t":24},{"o":{"x":0.65,"y":0},"i":{"x":0.35,"y":0},"s":[100,100],"t":48},{"o":{"x":0.65,"y":0},"i":{"x":0.35,"y":0},"s":[100,100],"t":72},{"o":{"x":0.65,"y":0},"i":{"x":0.35,"y":0},"s":[100,100],"t":216},{"s":[100,100],"t":240}]},"sk":{"a":0,"k":0},"p":{"a":1,"k":[{"o":{"x":0.65,"y":0},"i":{"x":0.35,"y":0},"s":[88.5,20.38],"t":0},{"o":{"x":0.65,"y":0},"i":{"x":0.35,"y":0},"s":[88.5,20.38],"t":24},{"o":{"x":0.65,"y":0},"i":{"x":0.35,"y":0},"s":[41.02,35.38],"t":48},{"o":{"x":0.65,"y":0},"i":{"x":0.35,"y":0},"s":[45.02,45.38],"t":72},{"o":{"x":0.65,"y":0},"i":{"x":0.35,"y":0},"s":[45.02,45.38],"t":216},{"s":[45.02,45.38],"t":240}]},"r":{"a":1,"k":[{"o":{"x":0.65,"y":0},"i":{"x":0.35,"y":0},"s":[0],"t":0},{"o":{"x":0.65,"y":0},"i":{"x":0.35,"y":0},"s":[0],"t":24},{"o":{"x":0.65,"y":0},"i":{"x":0.35,"y":0},"s":[0],"t":48},{"o":{"x":0.65,"y":0},"i":{"x":0.35,"y":0},"s":[0],"t":72},{"o":{"x":0.65,"y":0},"i":{"x":0.35,"y":0},"s":[0],"t":216},{"s":[0],"t":240}]},"sa":{"a":0,"k":0},"o":{"a":1,"k":[{"o":{"x":0.65,"y":0},"i":{"x":0.35,"y":0},"s":[100],"t":0},{"o":{"x":0.65,"y":0},"i":{"x":0.35,"y":0},"s":[100],"t":24},{"o":{"x":0.65,"y":0},"i":{"x":0.35,"y":0},"s":[100],"t":48},{"o":{"x":0.65,"y":0},"i":{"x":0.35,"y":0},"s":[100],"t":72},{"o":{"x":0.65,"y":0},"i":{"x":0.35,"y":0},"s":[100],"t":216},{"s":[100],"t":240}]}},"shapes":[{"ty":"sh","bm":0,"hd":false,"nm":"","d":1,"ks":{"a":1,"k":[{"o":{"x":0.65,"y":0},"i":{"x":0.35,"y":0},"s":[{"c":true,"i":[[0,0],[0,0.41],[0.41,0],[0,0]],"o":[[0.41,0],[0,-0.41],[0,0],[0,0]],"v":[[0.25,0.75],[1,0],[0.25,-0.75],[0.25,0.75]]}],"t":0},{"o":{"x":0.65,"y":0},"i":{"x":0.35,"y":0},"s":[{"c":true,"i":[[0,0],[0,0.41],[0.41,0],[0,0]],"o":[[0.41,0],[0,-0.41],[0,0],[0,0]],"v":[[0.25,0.75],[1,0],[0.25,-0.75],[0.25,0.75]]}],"t":24},{"o":{"x":0.65,"y":0},"i":{"x":0.35,"y":0},"s":[{"c":true,"i":[[0,0],[0,-0.41],[-0.41,0],[0,0]],"o":[[-0.41,0],[0,0.41],[0,0],[0,0]],"v":[[0,-0.75],[-0.75,0],[0,0.75],[0,-0.75]]}],"t":48},{"o":{"x":0.65,"y":0},"i":{"x":0.35,"y":0},"s":[{"c":true,"i":[[0,0],[0,-0.41],[-0.41,0],[0,0]],"o":[[-0.41,0],[0,0.41],[0,0],[0,0]],"v":[[0,-0.75],[-0.75,0],[0,0.75],[0,-0.75]]}],"t":72},{"o":{"x":0.65,"y":0},"i":{"x":0.35,"y":0},"s":[{"c":true,"i":[[0,0],[0,-0.41],[-0.41,0],[0,0]],"o":[[-0.41,0],[0,0.41],[0,0],[0,0]],"v":[[0,-0.75],[-0.75,0],[0,0.75],[0,-0.75]]}],"t":216},{"s":[{"c":true,"i":[[0,0],[0,-0.41],[-0.41,0],[0,0]],"o":[[-0.41,0],[0,0.41],[0,0],[0,0]],"v":[[0,-0.75],[-0.75,0],[0,0.75],[0,-0.75]]}],"t":240}]}},{"ty":"sh","bm":0,"hd":false,"nm":"","d":1,"ks":{"a":1,"k":[{"o":{"x":0.65,"y":0},"i":{"x":0.35,"y":0},"s":[{"c":true,"i":[[0,0],[0,-0.41],[-0.41,0],[0,0]],"o":[[-0.41,0],[0,0.41],[0,0],[0,0]],"v":[[0,-0.75],[-0.75,0],[0,0.75],[0,-0.75]]}],"t":0},{"o":{"x":0.65,"y":0},"i":{"x":0.35,"y":0},"s":[{"c":true,"i":[[0,0],[0,-0.41],[-0.41,0],[0,0]],"o":[[-0.41,0],[0,0.41],[0,0],[0,0]],"v":[[0,-0.75],[-0.75,0],[0,0.75],[0,-0.75]]}],"t":24},{"o":{"x":0.65,"y":0},"i":{"x":0.35,"y":0},"s":[{"c":true,"i":[[0,0],[0,0.41],[0.41,0],[0,0]],"o":[[0.41,0],[0,-0.41],[0,0],[0,0]],"v":[[3.75,0.75],[4.5,0],[3.75,-0.75],[3.75,0.75]]}],"t":48},{"o":{"x":0.65,"y":0},"i":{"x":0.35,"y":0},"s":[{"c":true,"i":[[0,0],[0,0.41],[0.41,0],[0,0]],"o":[[0.41,0],[0,-0.41],[0,0],[0,0]],"v":[[11.75,0.75],[12.5,0],[11.75,-0.75],[11.75,0.75]]}],"t":72},{"o":{"x":0.65,"y":0},"i":{"x":0.35,"y":0},"s":[{"c":true,"i":[[0,0],[0,0.41],[0.41,0],[0,0]],"o":[[0.41,0],[0,-0.41],[0,0],[0,0]],"v":[[11.75,0.75],[12.5,0],[11.75,-0.75],[11.75,0.75]]}],"t":216},{"s":[{"c":true,"i":[[0,0],[0,0.41],[0.41,0],[0,0]],"o":[[0.41,0],[0,-0.41],[0,0],[0,0]],"v":[[11.75,0.75],[12.5,0],[11.75,-0.75],[11.75,0.75]]}],"t":240}]}},{"ty":"sh","bm":0,"hd":false,"nm":"","d":1,"ks":{"a":1,"k":[{"o":{"x":0.65,"y":0},"i":{"x":0.35,"y":0},"s":[{"c":true,"i":[[0,0],[0,0],[0,0],[0,0],[0,0]],"o":[[0,0],[0,0],[0,0],[0,0],[0,0]],"v":[[0.25,-0.75],[0,-0.75],[0,0.75],[0.25,0.75],[0.25,-0.75]]}],"t":0},{"o":{"x":0.65,"y":0},"i":{"x":0.35,"y":0},"s":[{"c":true,"i":[[0,0],[0,0],[0,0],[0,0],[0,0]],"o":[[0,0],[0,0],[0,0],[0,0],[0,0]],"v":[[0.25,-0.75],[0,-0.75],[0,0.75],[0.25,0.75],[0.25,-0.75]]}],"t":24},{"o":{"x":0.65,"y":0},"i":{"x":0.35,"y":0},"s":[{"c":true,"i":[[0,0],[0,0],[0,0],[0,0],[0,0]],"o":[[0,0],[0,0],[0,0],[0,0],[0,0]],"v":[[0,0.75],[3.75,0.75],[3.75,-0.75],[0,-0.75],[0,0.75]]}],"t":48},{"o":{"x":0.65,"y":0},"i":{"x":0.35,"y":0},"s":[{"c":true,"i":[[0,0],[0,0],[0,0],[0,0],[0,0]],"o":[[0,0],[0,0],[0,0],[0,0],[0,0]],"v":[[0,0.75],[11.75,0.75],[11.75,-0.75],[0,-0.75],[0,0.75]]}],"t":72},{"o":{"x":0.65,"y":0},"i":{"x":0.35,"y":0},"s":[{"c":true,"i":[[0,0],[0,0],[0,0],[0,0],[0,0]],"o":[[0,0],[0,0],[0,0],[0,0],[0,0]],"v":[[0,0.75],[11.75,0.75],[11.75,-0.75],[0,-0.75],[0,0.75]]}],"t":216},{"s":[{"c":true,"i":[[0,0],[0,0],[0,0],[0,0],[0,0]],"o":[[0,0],[0,0],[0,0],[0,0],[0,0]],"v":[[0,0.75],[11.75,0.75],[11.75,-0.75],[0,-0.75],[0,0.75]]}],"t":240}]}},{"ty":"fl","bm":0,"hd":false,"nm":"","c":{"a":1,"k":[{"o":{"x":0.65,"y":0},"i":{"x":0.35,"y":0},"s":[0,0.3294,0.3137],"t":0},{"o":{"x":0.65,"y":0},"i":{"x":0.35,"y":0},"s":[0,0.3294,0.3137],"t":24},{"o":{"x":0.65,"y":0},"i":{"x":0.35,"y":0},"s":[0,0.3294,0.3137],"t":48},{"o":{"x":0.65,"y":0},"i":{"x":0.35,"y":0},"s":[0,0.3294,0.3137],"t":72},{"o":{"x":0.65,"y":0},"i":{"x":0.35,"y":0},"s":[0,0.3294,0.3137],"t":216},{"s":[0,0.3294,0.3137],"t":240}]},"r":1,"o":{"a":1,"k":[{"o":{"x":0.65,"y":0},"i":{"x":0.35,"y":0},"s":[100],"t":0},{"o":{"x":0.65,"y":0},"i":{"x":0.35,"y":0},"s":[100],"t":24},{"o":{"x":0.65,"y":0},"i":{"x":0.35,"y":0},"s":[100],"t":48},{"o":{"x":0.65,"y":0},"i":{"x":0.35,"y":0},"s":[100],"t":72},{"o":{"x":0.65,"y":0},"i":{"x":0.35,"y":0},"s":[100],"t":216},{"s":[100],"t":240}]}}],"ind":4},{"ty":4,"nm":"Ellipse 1","sr":1,"st":0,"op":241.06,"ip":0,"hd":false,"ddd":0,"bm":0,"hasMask":false,"td":1,"ao":0,"ks":{"a":{"a":1,"k":[{"o":{"x":0.65,"y":0},"i":{"x":0.35,"y":0},"s":[40,40],"t":0},{"o":{"x":0.65,"y":0},"i":{"x":0.35,"y":0},"s":[40,40],"t":24},{"o":{"x":0.65,"y":0},"i":{"x":0.35,"y":0},"s":[40,40],"t":48},{"o":{"x":0.65,"y":0},"i":{"x":0.35,"y":0},"s":[40,40],"t":72},{"o":{"x":0.65,"y":0},"i":{"x":0.35,"y":0},"s":[40,40],"t":216},{"s":[40,40],"t":240}]},"s":{"a":1,"k":[{"o":{"x":0.65,"y":0},"i":{"x":0.35,"y":0},"s":[100,100],"t":0},{"o":{"x":0.65,"y":0},"i":{"x":0.35,"y":0},"s":[100,100],"t":24},{"o":{"x":0.65,"y":0},"i":{"x":0.35,"y":0},"s":[100,100],"t":48},{"o":{"x":0.65,"y":0},"i":{"x":0.35,"y":0},"s":[100,100],"t":72},{"o":{"x":0.65,"y":0},"i":{"x":0.35,"y":0},"s":[100,100],"t":216},{"s":[100,100],"t":240}]},"sk":{"a":0,"k":0},"p":{"a":1,"k":[{"o":{"x":0.65,"y":0},"i":{"x":0.35,"y":0},"s":[40,40],"t":0},{"o":{"x":0.65,"y":0},"i":{"x":0.35,"y":0},"s":[40,40],"t":24},{"o":{"x":0.65,"y":0},"i":{"x":0.35,"y":0},"s":[40,40],"t":48},{"o":{"x":0.65,"y":0},"i":{"x":0.35,"y":0},"s":[40,40],"t":72},{"o":{"x":0.65,"y":0},"i":{"x":0.35,"y":0},"s":[40,40],"t":216},{"s":[40,40],"t":240}]},"r":{"a":1,"k":[{"o":{"x":0.65,"y":0},"i":{"x":0.35,"y":0},"s":[0],"t":0},{"o":{"x":0.65,"y":0},"i":{"x":0.35,"y":0},"s":[0],"t":24},{"o":{"x":0.65,"y":0},"i":{"x":0.35,"y":0},"s":[0],"t":48},{"o":{"x":0.65,"y":0},"i":{"x":0.35,"y":0},"s":[0],"t":72},{"o":{"x":0.65,"y":0},"i":{"x":0.35,"y":0},"s":[0],"t":216},{"s":[0],"t":240}]},"sa":{"a":0,"k":0},"o":{"a":1,"k":[{"o":{"x":0.65,"y":0},"i":{"x":0.35,"y":0},"s":[100],"t":0},{"o":{"x":0.65,"y":0},"i":{"x":0.35,"y":0},"s":[100],"t":24},{"o":{"x":0.65,"y":0},"i":{"x":0.35,"y":0},"s":[100],"t":48},{"o":{"x":0.65,"y":0},"i":{"x":0.35,"y":0},"s":[100],"t":72},{"o":{"x":0.65,"y":0},"i":{"x":0.35,"y":0},"s":[100],"t":216},{"s":[100],"t":240}]}},"shapes":[{"ty":"sh","bm":0,"hd":false,"nm":"","d":1,"ks":{"a":1,"k":[{"o":{"x":0.65,"y":0},"i":{"x":0.35,"y":0},"s":[{"c":true,"i":[[0,0],[22.09,0],[0,22.09],[-22.09,0],[0,-22.09]],"o":[[0,22.09],[-22.09,0],[0,-22.09],[22.09,0],[0,0]],"v":[[80,40],[40,80],[0,40],[40,0],[80,40]]}],"t":0},{"o":{"x":0.65,"y":0},"i":{"x":0.35,"y":0},"s":[{"c":true,"i":[[0,0],[22.09,0],[0,22.09],[-22.09,0],[0,-22.09]],"o":[[0,22.09],[-22.09,0],[0,-22.09],[22.09,0],[0,0]],"v":[[80,40],[40,80],[0,40],[40,0],[80,40]]}],"t":24},{"o":{"x":0.65,"y":0},"i":{"x":0.35,"y":0},"s":[{"c":true,"i":[[0,0],[22.09,0],[0,22.09],[-22.09,0],[0,-22.09]],"o":[[0,22.09],[-22.09,0],[0,-22.09],[22.09,0],[0,0]],"v":[[80,40],[40,80],[0,40],[40,0],[80,40]]}],"t":48},{"o":{"x":0.65,"y":0},"i":{"x":0.35,"y":0},"s":[{"c":true,"i":[[0,0],[22.09,0],[0,22.09],[-22.09,0],[0,-22.09]],"o":[[0,22.09],[-22.09,0],[0,-22.09],[22.09,0],[0,0]],"v":[[80,40],[40,80],[0,40],[40,0],[80,40]]}],"t":72},{"o":{"x":0.65,"y":0},"i":{"x":0.35,"y":0},"s":[{"c":true,"i":[[0,0],[22.09,0],[0,22.09],[-22.09,0],[0,-22.09]],"o":[[0,22.09],[-22.09,0],[0,-22.09],[22.09,0],[0,0]],"v":[[80,40],[40,80],[0,40],[40,0],[80,40]]}],"t":216},{"s":[{"c":true,"i":[[0,0],[22.09,0],[0,22.09],[-22.09,0],[0,-22.09]],"o":[[0,22.09],[-22.09,0],[0,-22.09],[22.09,0],[0,0]],"v":[[80,40],[40,80],[0,40],[40,0],[80,40]]}],"t":240}]}},{"ty":"fl","bm":0,"hd":false,"nm":"","c":{"a":1,"k":[{"o":{"x":0.65,"y":0},"i":{"x":0.35,"y":0},"s":[0.7608,0.8392,0.6392],"t":0},{"o":{"x":0.65,"y":0},"i":{"x":0.35,"y":0},"s":[0.7608,0.8392,0.6392],"t":24},{"o":{"x":0.65,"y":0},"i":{"x":0.35,"y":0},"s":[0.7608,0.8392,0.6392],"t":48},{"o":{"x":0.65,"y":0},"i":{"x":0.35,"y":0},"s":[0.7608,0.8392,0.6392],"t":72},{"o":{"x":0.65,"y":0},"i":{"x":0.35,"y":0},"s":[0.7608,0.8392,0.6392],"t":216},{"s":[0.7608,0.8392,0.6392],"t":240}]},"r":1,"o":{"a":1,"k":[{"o":{"x":0.65,"y":0},"i":{"x":0.35,"y":0},"s":[100],"t":0},{"o":{"x":0.65,"y":0},"i":{"x":0.35,"y":0},"s":[100],"t":24},{"o":{"x":0.65,"y":0},"i":{"x":0.35,"y":0},"s":[100],"t":48},{"o":{"x":0.65,"y":0},"i":{"x":0.35,"y":0},"s":[100],"t":72},{"o":{"x":0.65,"y":0},"i":{"x":0.35,"y":0},"s":[100],"t":216},{"s":[100],"t":240}]}}],"ind":5},{"ty":4,"nm":"Dot 2","sr":1,"st":0,"op":241.06,"ip":0,"hd":false,"ddd":0,"bm":0,"tt":1,"hasMask":false,"ao":0,"ks":{"a":{"a":1,"k":[{"o":{"x":0.65,"y":0},"i":{"x":0.35,"y":0},"s":[2.5,2.5],"t":0},{"o":{"x":0.65,"y":0},"i":{"x":0.35,"y":0},"s":[2.5,2.5],"t":24},{"o":{"x":0.65,"y":0},"i":{"x":0.35,"y":0},"s":[2.5,2.5],"t":48},{"o":{"x":0.65,"y":0},"i":{"x":0.35,"y":0},"s":[2.5,2.5],"t":72},{"o":{"x":0.65,"y":0},"i":{"x":0.35,"y":0},"s":[2.5,2.5],"t":216},{"s":[2.5,2.5],"t":240}]},"s":{"a":1,"k":[{"o":{"x":0.65,"y":0},"i":{"x":0.35,"y":0},"s":[100,100],"t":0},{"o":{"x":0.65,"y":0},"i":{"x":0.35,"y":0},"s":[100,100],"t":24},{"o":{"x":0.65,"y":0},"i":{"x":0.35,"y":0},"s":[100,100],"t":48},{"o":{"x":0.65,"y":0},"i":{"x":0.35,"y":0},"s":[100,100],"t":72},{"o":{"x":0.65,"y":0},"i":{"x":0.35,"y":0},"s":[100,100],"t":216},{"s":[100,100],"t":240}]},"sk":{"a":0,"k":0},"p":{"a":1,"k":[{"o":{"x":0.65,"y":0},"i":{"x":0.35,"y":0},"s":[88.5,20.5],"t":0},{"o":{"x":0.65,"y":0},"i":{"x":0.35,"y":0},"s":[88.5,20.5],"t":24},{"o":{"x":0.65,"y":0},"i":{"x":0.35,"y":0},"s":[32.02,35.5],"t":48},{"o":{"x":0.65,"y":0},"i":{"x":0.35,"y":0},"s":[32.02,45.5],"t":72},{"o":{"x":0.65,"y":0},"i":{"x":0.35,"y":0},"s":[32.02,45.5],"t":216},{"s":[32.02,45.5],"t":240}]},"r":{"a":1,"k":[{"o":{"x":0.65,"y":0},"i":{"x":0.35,"y":0},"s":[0],"t":0},{"o":{"x":0.65,"y":0},"i":{"x":0.35,"y":0},"s":[0],"t":24},{"o":{"x":0.65,"y":0},"i":{"x":0.35,"y":0},"s":[0],"t":48},{"o":{"x":0.65,"y":0},"i":{"x":0.35,"y":0},"s":[0],"t":72},{"o":{"x":0.65,"y":0},"i":{"x":0.35,"y":0},"s":[0],"t":216},{"s":[0],"t":240}]},"sa":{"a":0,"k":0},"o":{"a":1,"k":[{"o":{"x":0.65,"y":0},"i":{"x":0.35,"y":0},"s":[100],"t":0},{"o":{"x":0.65,"y":0},"i":{"x":0.35,"y":0},"s":[100],"t":24},{"o":{"x":0.65,"y":0},"i":{"x":0.35,"y":0},"s":[100],"t":48},{"o":{"x":0.65,"y":0},"i":{"x":0.35,"y":0},"s":[100],"t":72},{"o":{"x":0.65,"y":0},"i":{"x":0.35,"y":0},"s":[100],"t":216},{"s":[100],"t":240}]}},"shapes":[{"ty":"sh","bm":0,"hd":false,"nm":"","d":1,"ks":{"a":1,"k":[{"o":{"x":0.65,"y":0},"i":{"x":0.35,"y":0},"s":[{"c":true,"i":[[0,0],[1.38,0],[0,1.38],[-1.38,0],[0,-1.38]],"o":[[0,1.38],[-1.38,0],[0,-1.38],[1.38,0],[0,0]],"v":[[5,2.5],[2.5,5],[0,2.5],[2.5,0],[5,2.5]]}],"t":0},{"o":{"x":0.65,"y":0},"i":{"x":0.35,"y":0},"s":[{"c":true,"i":[[0,0],[1.38,0],[0,1.38],[-1.38,0],[0,-1.38]],"o":[[0,1.38],[-1.38,0],[0,-1.38],[1.38,0],[0,0]],"v":[[5,2.5],[2.5,5],[0,2.5],[2.5,0],[5,2.5]]}],"t":24},{"o":{"x":0.65,"y":0},"i":{"x":0.35,"y":0},"s":[{"c":true,"i":[[0,0],[1.38,0],[0,1.38],[-1.38,0],[0,-1.38]],"o":[[0,1.38],[-1.38,0],[0,-1.38],[1.38,0],[0,0]],"v":[[5,2.5],[2.5,5],[0,2.5],[2.5,0],[5,2.5]]}],"t":48},{"o":{"x":0.65,"y":0},"i":{"x":0.35,"y":0},"s":[{"c":true,"i":[[0,0],[1.38,0],[0,1.38],[-1.38,0],[0,-1.38]],"o":[[0,1.38],[-1.38,0],[0,-1.38],[1.38,0],[0,0]],"v":[[5,2.5],[2.5,5],[0,2.5],[2.5,0],[5,2.5]]}],"t":72},{"o":{"x":0.65,"y":0},"i":{"x":0.35,"y":0},"s":[{"c":true,"i":[[0,0],[1.38,0],[0,1.38],[-1.38,0],[0,-1.38]],"o":[[0,1.38],[-1.38,0],[0,-1.38],[1.38,0],[0,0]],"v":[[5,2.5],[2.5,5],[0,2.5],[2.5,0],[5,2.5]]}],"t":216},{"s":[{"c":true,"i":[[0,0],[1.38,0],[0,1.38],[-1.38,0],[0,-1.38]],"o":[[0,1.38],[-1.38,0],[0,-1.38],[1.38,0],[0,0]],"v":[[5,2.5],[2.5,5],[0,2.5],[2.5,0],[5,2.5]]}],"t":240}]}},{"ty":"fl","bm":0,"hd":false,"nm":"","c":{"a":1,"k":[{"o":{"x":0.65,"y":0},"i":{"x":0.35,"y":0},"s":[0,0.3294,0.3137],"t":0},{"o":{"x":0.65,"y":0},"i":{"x":0.35,"y":0},"s":[0,0.3294,0.3137],"t":24},{"o":{"x":0.65,"y":0},"i":{"x":0.35,"y":0},"s":[0,0.3294,0.3137],"t":48},{"o":{"x":0.65,"y":0},"i":{"x":0.35,"y":0},"s":[0,0.3294,0.3137],"t":72},{"o":{"x":0.65,"y":0},"i":{"x":0.35,"y":0},"s":[0,0.3294,0.3137],"t":216},{"s":[0,0.3294,0.3137],"t":240}]},"r":1,"o":{"a":1,"k":[{"o":{"x":0.65,"y":0},"i":{"x":0.35,"y":0},"s":[100],"t":0},{"o":{"x":0.65,"y":0},"i":{"x":0.35,"y":0},"s":[100],"t":24},{"o":{"x":0.65,"y":0},"i":{"x":0.35,"y":0},"s":[100],"t":48},{"o":{"x":0.65,"y":0},"i":{"x":0.35,"y":0},"s":[100],"t":72},{"o":{"x":0.65,"y":0},"i":{"x":0.35,"y":0},"s":[100],"t":216},{"s":[100],"t":240}]}}],"ind":6},{"ty":4,"nm":"Ellipse 1","sr":1,"st":0,"op":241.06,"ip":0,"hd":false,"ddd":0,"bm":0,"hasMask":false,"td":1,"ao":0,"ks":{"a":{"a":1,"k":[{"o":{"x":0.65,"y":0},"i":{"x":0.35,"y":0},"s":[40,40],"t":0},{"o":{"x":0.65,"y":0},"i":{"x":0.35,"y":0},"s":[40,40],"t":24},{"o":{"x":0.65,"y":0},"i":{"x":0.35,"y":0},"s":[40,40],"t":48},{"o":{"x":0.65,"y":0},"i":{"x":0.35,"y":0},"s":[40,40],"t":72},{"o":{"x":0.65,"y":0},"i":{"x":0.35,"y":0},"s":[40,40],"t":216},{"s":[40,40],"t":240}]},"s":{"a":1,"k":[{"o":{"x":0.65,"y":0},"i":{"x":0.35,"y":0},"s":[100,100],"t":0},{"o":{"x":0.65,"y":0},"i":{"x":0.35,"y":0},"s":[100,100],"t":24},{"o":{"x":0.65,"y":0},"i":{"x":0.35,"y":0},"s":[100,100],"t":48},{"o":{"x":0.65,"y":0},"i":{"x":0.35,"y":0},"s":[100,100],"t":72},{"o":{"x":0.65,"y":0},"i":{"x":0.35,"y":0},"s":[100,100],"t":216},{"s":[100,100],"t":240}]},"sk":{"a":0,"k":0},"p":{"a":1,"k":[{"o":{"x":0.65,"y":0},"i":{"x":0.35,"y":0},"s":[40,40],"t":0},{"o":{"x":0.65,"y":0},"i":{"x":0.35,"y":0},"s":[40,40],"t":24},{"o":{"x":0.65,"y":0},"i":{"x":0.35,"y":0},"s":[40,40],"t":48},{"o":{"x":0.65,"y":0},"i":{"x":0.35,"y":0},"s":[40,40],"t":72},{"o":{"x":0.65,"y":0},"i":{"x":0.35,"y":0},"s":[40,40],"t":216},{"s":[40,40],"t":240}]},"r":{"a":1,"k":[{"o":{"x":0.65,"y":0},"i":{"x":0.35,"y":0},"s":[0],"t":0},{"o":{"x":0.65,"y":0},"i":{"x":0.35,"y":0},"s":[0],"t":24},{"o":{"x":0.65,"y":0},"i":{"x":0.35,"y":0},"s":[0],"t":48},{"o":{"x":0.65,"y":0},"i":{"x":0.35,"y":0},"s":[0],"t":72},{"o":{"x":0.65,"y":0},"i":{"x":0.35,"y":0},"s":[0],"t":216},{"s":[0],"t":240}]},"sa":{"a":0,"k":0},"o":{"a":1,"k":[{"o":{"x":0.65,"y":0},"i":{"x":0.35,"y":0},"s":[100],"t":0},{"o":{"x":0.65,"y":0},"i":{"x":0.35,"y":0},"s":[100],"t":24},{"o":{"x":0.65,"y":0},"i":{"x":0.35,"y":0},"s":[100],"t":48},{"o":{"x":0.65,"y":0},"i":{"x":0.35,"y":0},"s":[100],"t":72},{"o":{"x":0.65,"y":0},"i":{"x":0.35,"y":0},"s":[100],"t":216},{"s":[100],"t":240}]}},"shapes":[{"ty":"sh","bm":0,"hd":false,"nm":"","d":1,"ks":{"a":1,"k":[{"o":{"x":0.65,"y":0},"i":{"x":0.35,"y":0},"s":[{"c":true,"i":[[0,0],[22.09,0],[0,22.09],[-22.09,0],[0,-22.09]],"o":[[0,22.09],[-22.09,0],[0,-22.09],[22.09,0],[0,0]],"v":[[80,40],[40,80],[0,40],[40,0],[80,40]]}],"t":0},{"o":{"x":0.65,"y":0},"i":{"x":0.35,"y":0},"s":[{"c":true,"i":[[0,0],[22.09,0],[0,22.09],[-22.09,0],[0,-22.09]],"o":[[0,22.09],[-22.09,0],[0,-22.09],[22.09,0],[0,0]],"v":[[80,40],[40,80],[0,40],[40,0],[80,40]]}],"t":24},{"o":{"x":0.65,"y":0},"i":{"x":0.35,"y":0},"s":[{"c":true,"i":[[0,0],[22.09,0],[0,22.09],[-22.09,0],[0,-22.09]],"o":[[0,22.09],[-22.09,0],[0,-22.09],[22.09,0],[0,0]],"v":[[80,40],[40,80],[0,40],[40,0],[80,40]]}],"t":48},{"o":{"x":0.65,"y":0},"i":{"x":0.35,"y":0},"s":[{"c":true,"i":[[0,0],[22.09,0],[0,22.09],[-22.09,0],[0,-22.09]],"o":[[0,22.09],[-22.09,0],[0,-22.09],[22.09,0],[0,0]],"v":[[80,40],[40,80],[0,40],[40,0],[80,40]]}],"t":72},{"o":{"x":0.65,"y":0},"i":{"x":0.35,"y":0},"s":[{"c":true,"i":[[0,0],[22.09,0],[0,22.09],[-22.09,0],[0,-22.09]],"o":[[0,22.09],[-22.09,0],[0,-22.09],[22.09,0],[0,0]],"v":[[80,40],[40,80],[0,40],[40,0],[80,40]]}],"t":216},{"s":[{"c":true,"i":[[0,0],[22.09,0],[0,22.09],[-22.09,0],[0,-22.09]],"o":[[0,22.09],[-22.09,0],[0,-22.09],[22.09,0],[0,0]],"v":[[80,40],[40,80],[0,40],[40,0],[80,40]]}],"t":240}]}},{"ty":"fl","bm":0,"hd":false,"nm":"","c":{"a":1,"k":[{"o":{"x":0.65,"y":0},"i":{"x":0.35,"y":0},"s":[0.7608,0.8392,0.6392],"t":0},{"o":{"x":0.65,"y":0},"i":{"x":0.35,"y":0},"s":[0.7608,0.8392,0.6392],"t":24},{"o":{"x":0.65,"y":0},"i":{"x":0.35,"y":0},"s":[0.7608,0.8392,0.6392],"t":48},{"o":{"x":0.65,"y":0},"i":{"x":0.35,"y":0},"s":[0.7608,0.8392,0.6392],"t":72},{"o":{"x":0.65,"y":0},"i":{"x":0.35,"y":0},"s":[0.7608,0.8392,0.6392],"t":216},{"s":[0.7608,0.8392,0.6392],"t":240}]},"r":1,"o":{"a":1,"k":[{"o":{"x":0.65,"y":0},"i":{"x":0.35,"y":0},"s":[100],"t":0},{"o":{"x":0.65,"y":0},"i":{"x":0.35,"y":0},"s":[100],"t":24},{"o":{"x":0.65,"y":0},"i":{"x":0.35,"y":0},"s":[100],"t":48},{"o":{"x":0.65,"y":0},"i":{"x":0.35,"y":0},"s":[100],"t":72},{"o":{"x":0.65,"y":0},"i":{"x":0.35,"y":0},"s":[100],"t":216},{"s":[100],"t":240}]}}],"ind":7},{"ty":4,"nm":"Line 1","sr":1,"st":0,"op":241.06,"ip":0,"hd":false,"ddd":0,"bm":0,"tt":1,"hasMask":false,"ao":0,"ks":{"a":{"a":1,"k":[{"o":{"x":0.65,"y":0},"i":{"x":0.35,"y":0},"s":[0.13,0],"t":0},{"o":{"x":0.65,"y":0},"i":{"x":0.35,"y":0},"s":[0.13,0],"t":24},{"o":{"x":0.65,"y":0},"i":{"x":0.35,"y":0},"s":[1.88,0],"t":48},{"o":{"x":0.65,"y":0},"i":{"x":0.35,"y":0},"s":[5.88,0],"t":72},{"o":{"x":0.65,"y":0},"i":{"x":0.35,"y":0},"s":[5.88,0],"t":216},{"s":[5.88,0],"t":240}]},"s":{"a":1,"k":[{"o":{"x":0.65,"y":0},"i":{"x":0.35,"y":0},"s":[100,100],"t":0},{"o":{"x":0.65,"y":0},"i":{"x":0.35,"y":0},"s":[100,100],"t":24},{"o":{"x":0.65,"y":0},"i":{"x":0.35,"y":0},"s":[100,100],"t":48},{"o":{"x":0.65,"y":0},"i":{"x":0.35,"y":0},"s":[100,100],"t":72},{"o":{"x":0.65,"y":0},"i":{"x":0.35,"y":0},"s":[100,100],"t":216},{"s":[100,100],"t":240}]},"sk":{"a":0,"k":0},"p":{"a":1,"k":[{"o":{"x":0.65,"y":0},"i":{"x":0.35,"y":0},"s":[88.5,20.38],"t":0},{"o":{"x":0.65,"y":0},"i":{"x":0.35,"y":0},"s":[88.5,20.38],"t":24},{"o":{"x":0.65,"y":0},"i":{"x":0.35,"y":0},"s":[41.02,35.38],"t":48},{"o":{"x":0.65,"y":0},"i":{"x":0.35,"y":0},"s":[45.02,35.38],"t":72},{"o":{"x":0.65,"y":0},"i":{"x":0.35,"y":0},"s":[45.02,35.38],"t":216},{"s":[45.02,35.38],"t":240}]},"r":{"a":1,"k":[{"o":{"x":0.65,"y":0},"i":{"x":0.35,"y":0},"s":[0],"t":0},{"o":{"x":0.65,"y":0},"i":{"x":0.35,"y":0},"s":[0],"t":24},{"o":{"x":0.65,"y":0},"i":{"x":0.35,"y":0},"s":[0],"t":48},{"o":{"x":0.65,"y":0},"i":{"x":0.35,"y":0},"s":[0],"t":72},{"o":{"x":0.65,"y":0},"i":{"x":0.35,"y":0},"s":[0],"t":216},{"s":[0],"t":240}]},"sa":{"a":0,"k":0},"o":{"a":1,"k":[{"o":{"x":0.65,"y":0},"i":{"x":0.35,"y":0},"s":[100],"t":0},{"o":{"x":0.65,"y":0},"i":{"x":0.35,"y":0},"s":[100],"t":24},{"o":{"x":0.65,"y":0},"i":{"x":0.35,"y":0},"s":[100],"t":48},{"o":{"x":0.65,"y":0},"i":{"x":0.35,"y":0},"s":[100],"t":72},{"o":{"x":0.65,"y":0},"i":{"x":0.35,"y":0},"s":[100],"t":216},{"s":[100],"t":240}]}},"shapes":[{"ty":"sh","bm":0,"hd":false,"nm":"","d":1,"ks":{"a":1,"k":[{"o":{"x":0.65,"y":0},"i":{"x":0.35,"y":0},"s":[{"c":true,"i":[[0,0],[0,0.41],[0.41,0],[0,0]],"o":[[0.41,0],[0,-0.41],[0,0],[0,0]],"v":[[0.25,0.75],[1,0],[0.25,-0.75],[0.25,0.75]]}],"t":0},{"o":{"x":0.65,"y":0},"i":{"x":0.35,"y":0},"s":[{"c":true,"i":[[0,0],[0,0.41],[0.41,0],[0,0]],"o":[[0.41,0],[0,-0.41],[0,0],[0,0]],"v":[[0.25,0.75],[1,0],[0.25,-0.75],[0.25,0.75]]}],"t":24},{"o":{"x":0.65,"y":0},"i":{"x":0.35,"y":0},"s":[{"c":true,"i":[[0,0],[0,-0.41],[-0.41,0],[0,0]],"o":[[-0.41,0],[0,0.41],[0,0],[0,0]],"v":[[0,-0.75],[-0.75,0],[0,0.75],[0,-0.75]]}],"t":48},{"o":{"x":0.65,"y":0},"i":{"x":0.35,"y":0},"s":[{"c":true,"i":[[0,0],[0,-0.41],[-0.41,0],[0,0]],"o":[[-0.41,0],[0,0.41],[0,0],[0,0]],"v":[[0,-0.75],[-0.75,0],[0,0.75],[0,-0.75]]}],"t":72},{"o":{"x":0.65,"y":0},"i":{"x":0.35,"y":0},"s":[{"c":true,"i":[[0,0],[0,-0.41],[-0.41,0],[0,0]],"o":[[-0.41,0],[0,0.41],[0,0],[0,0]],"v":[[0,-0.75],[-0.75,0],[0,0.75],[0,-0.75]]}],"t":216},{"s":[{"c":true,"i":[[0,0],[0,-0.41],[-0.41,0],[0,0]],"o":[[-0.41,0],[0,0.41],[0,0],[0,0]],"v":[[0,-0.75],[-0.75,0],[0,0.75],[0,-0.75]]}],"t":240}]}},{"ty":"sh","bm":0,"hd":false,"nm":"","d":1,"ks":{"a":1,"k":[{"o":{"x":0.65,"y":0},"i":{"x":0.35,"y":0},"s":[{"c":true,"i":[[0,0],[0,-0.41],[-0.41,0],[0,0]],"o":[[-0.41,0],[0,0.41],[0,0],[0,0]],"v":[[0,-0.75],[-0.75,0],[0,0.75],[0,-0.75]]}],"t":0},{"o":{"x":0.65,"y":0},"i":{"x":0.35,"y":0},"s":[{"c":true,"i":[[0,0],[0,-0.41],[-0.41,0],[0,0]],"o":[[-0.41,0],[0,0.41],[0,0],[0,0]],"v":[[0,-0.75],[-0.75,0],[0,0.75],[0,-0.75]]}],"t":24},{"o":{"x":0.65,"y":0},"i":{"x":0.35,"y":0},"s":[{"c":true,"i":[[0,0],[0,0.41],[0.41,0],[0,0]],"o":[[0.41,0],[0,-0.41],[0,0],[0,0]],"v":[[3.75,0.75],[4.5,0],[3.75,-0.75],[3.75,0.75]]}],"t":48},{"o":{"x":0.65,"y":0},"i":{"x":0.35,"y":0},"s":[{"c":true,"i":[[0,0],[0,0.41],[0.41,0],[0,0]],"o":[[0.41,0],[0,-0.41],[0,0],[0,0]],"v":[[11.75,0.75],[12.5,0],[11.75,-0.75],[11.75,0.75]]}],"t":72},{"o":{"x":0.65,"y":0},"i":{"x":0.35,"y":0},"s":[{"c":true,"i":[[0,0],[0,0.41],[0.41,0],[0,0]],"o":[[0.41,0],[0,-0.41],[0,0],[0,0]],"v":[[11.75,0.75],[12.5,0],[11.75,-0.75],[11.75,0.75]]}],"t":216},{"s":[{"c":true,"i":[[0,0],[0,0.41],[0.41,0],[0,0]],"o":[[0.41,0],[0,-0.41],[0,0],[0,0]],"v":[[11.75,0.75],[12.5,0],[11.75,-0.75],[11.75,0.75]]}],"t":240}]}},{"ty":"sh","bm":0,"hd":false,"nm":"","d":1,"ks":{"a":1,"k":[{"o":{"x":0.65,"y":0},"i":{"x":0.35,"y":0},"s":[{"c":true,"i":[[0,0],[0,0],[0,0],[0,0],[0,0]],"o":[[0,0],[0,0],[0,0],[0,0],[0,0]],"v":[[0.25,-0.75],[0,-0.75],[0,0.75],[0.25,0.75],[0.25,-0.75]]}],"t":0},{"o":{"x":0.65,"y":0},"i":{"x":0.35,"y":0},"s":[{"c":true,"i":[[0,0],[0,0],[0,0],[0,0],[0,0]],"o":[[0,0],[0,0],[0,0],[0,0],[0,0]],"v":[[0.25,-0.75],[0,-0.75],[0,0.75],[0.25,0.75],[0.25,-0.75]]}],"t":24},{"o":{"x":0.65,"y":0},"i":{"x":0.35,"y":0},"s":[{"c":true,"i":[[0,0],[0,0],[0,0],[0,0],[0,0]],"o":[[0,0],[0,0],[0,0],[0,0],[0,0]],"v":[[0,0.75],[3.75,0.75],[3.75,-0.75],[0,-0.75],[0,0.75]]}],"t":48},{"o":{"x":0.65,"y":0},"i":{"x":0.35,"y":0},"s":[{"c":true,"i":[[0,0],[0,0],[0,0],[0,0],[0,0]],"o":[[0,0],[0,0],[0,0],[0,0],[0,0]],"v":[[0,0.75],[11.75,0.75],[11.75,-0.75],[0,-0.75],[0,0.75]]}],"t":72},{"o":{"x":0.65,"y":0},"i":{"x":0.35,"y":0},"s":[{"c":true,"i":[[0,0],[0,0],[0,0],[0,0],[0,0]],"o":[[0,0],[0,0],[0,0],[0,0],[0,0]],"v":[[0,0.75],[11.75,0.75],[11.75,-0.75],[0,-0.75],[0,0.75]]}],"t":216},{"s":[{"c":true,"i":[[0,0],[0,0],[0,0],[0,0],[0,0]],"o":[[0,0],[0,0],[0,0],[0,0],[0,0]],"v":[[0,0.75],[11.75,0.75],[11.75,-0.75],[0,-0.75],[0,0.75]]}],"t":240}]}},{"ty":"fl","bm":0,"hd":false,"nm":"","c":{"a":1,"k":[{"o":{"x":0.65,"y":0},"i":{"x":0.35,"y":0},"s":[0,0.3294,0.3137],"t":0},{"o":{"x":0.65,"y":0},"i":{"x":0.35,"y":0},"s":[0,0.3294,0.3137],"t":24},{"o":{"x":0.65,"y":0},"i":{"x":0.35,"y":0},"s":[0,0.3294,0.3137],"t":48},{"o":{"x":0.65,"y":0},"i":{"x":0.35,"y":0},"s":[0,0.3294,0.3137],"t":72},{"o":{"x":0.65,"y":0},"i":{"x":0.35,"y":0},"s":[0,0.3294,0.3137],"t":216},{"s":[0,0.3294,0.3137],"t":240}]},"r":1,"o":{"a":1,"k":[{"o":{"x":0.65,"y":0},"i":{"x":0.35,"y":0},"s":[100],"t":0},{"o":{"x":0.65,"y":0},"i":{"x":0.35,"y":0},"s":[100],"t":24},{"o":{"x":0.65,"y":0},"i":{"x":0.35,"y":0},"s":[100],"t":48},{"o":{"x":0.65,"y":0},"i":{"x":0.35,"y":0},"s":[100],"t":72},{"o":{"x":0.65,"y":0},"i":{"x":0.35,"y":0},"s":[100],"t":216},{"s":[100],"t":240}]}}],"ind":8},{"ty":4,"nm":"Ellipse 1","sr":1,"st":0,"op":241.06,"ip":0,"hd":false,"ddd":0,"bm":0,"hasMask":false,"td":1,"ao":0,"ks":{"a":{"a":1,"k":[{"o":{"x":0.65,"y":0},"i":{"x":0.35,"y":0},"s":[40,40],"t":0},{"o":{"x":0.65,"y":0},"i":{"x":0.35,"y":0},"s":[40,40],"t":24},{"o":{"x":0.65,"y":0},"i":{"x":0.35,"y":0},"s":[40,40],"t":48},{"o":{"x":0.65,"y":0},"i":{"x":0.35,"y":0},"s":[40,40],"t":72},{"o":{"x":0.65,"y":0},"i":{"x":0.35,"y":0},"s":[40,40],"t":216},{"s":[40,40],"t":240}]},"s":{"a":1,"k":[{"o":{"x":0.65,"y":0},"i":{"x":0.35,"y":0},"s":[100,100],"t":0},{"o":{"x":0.65,"y":0},"i":{"x":0.35,"y":0},"s":[100,100],"t":24},{"o":{"x":0.65,"y":0},"i":{"x":0.35,"y":0},"s":[100,100],"t":48},{"o":{"x":0.65,"y":0},"i":{"x":0.35,"y":0},"s":[100,100],"t":72},{"o":{"x":0.65,"y":0},"i":{"x":0.35,"y":0},"s":[100,100],"t":216},{"s":[100,100],"t":240}]},"sk":{"a":0,"k":0},"p":{"a":1,"k":[{"o":{"x":0.65,"y":0},"i":{"x":0.35,"y":0},"s":[40,40],"t":0},{"o":{"x":0.65,"y":0},"i":{"x":0.35,"y":0},"s":[40,40],"t":24},{"o":{"x":0.65,"y":0},"i":{"x":0.35,"y":0},"s":[40,40],"t":48},{"o":{"x":0.65,"y":0},"i":{"x":0.35,"y":0},"s":[40,40],"t":72},{"o":{"x":0.65,"y":0},"i":{"x":0.35,"y":0},"s":[40,40],"t":216},{"s":[40,40],"t":240}]},"r":{"a":1,"k":[{"o":{"x":0.65,"y":0},"i":{"x":0.35,"y":0},"s":[0],"t":0},{"o":{"x":0.65,"y":0},"i":{"x":0.35,"y":0},"s":[0],"t":24},{"o":{"x":0.65,"y":0},"i":{"x":0.35,"y":0},"s":[0],"t":48},{"o":{"x":0.65,"y":0},"i":{"x":0.35,"y":0},"s":[0],"t":72},{"o":{"x":0.65,"y":0},"i":{"x":0.35,"y":0},"s":[0],"t":216},{"s":[0],"t":240}]},"sa":{"a":0,"k":0},"o":{"a":1,"k":[{"o":{"x":0.65,"y":0},"i":{"x":0.35,"y":0},"s":[100],"t":0},{"o":{"x":0.65,"y":0},"i":{"x":0.35,"y":0},"s":[100],"t":24},{"o":{"x":0.65,"y":0},"i":{"x":0.35,"y":0},"s":[100],"t":48},{"o":{"x":0.65,"y":0},"i":{"x":0.35,"y":0},"s":[100],"t":72},{"o":{"x":0.65,"y":0},"i":{"x":0.35,"y":0},"s":[100],"t":216},{"s":[100],"t":240}]}},"shapes":[{"ty":"sh","bm":0,"hd":false,"nm":"","d":1,"ks":{"a":1,"k":[{"o":{"x":0.65,"y":0},"i":{"x":0.35,"y":0},"s":[{"c":true,"i":[[0,0],[22.09,0],[0,22.09],[-22.09,0],[0,-22.09]],"o":[[0,22.09],[-22.09,0],[0,-22.09],[22.09,0],[0,0]],"v":[[80,40],[40,80],[0,40],[40,0],[80,40]]}],"t":0},{"o":{"x":0.65,"y":0},"i":{"x":0.35,"y":0},"s":[{"c":true,"i":[[0,0],[22.09,0],[0,22.09],[-22.09,0],[0,-22.09]],"o":[[0,22.09],[-22.09,0],[0,-22.09],[22.09,0],[0,0]],"v":[[80,40],[40,80],[0,40],[40,0],[80,40]]}],"t":24},{"o":{"x":0.65,"y":0},"i":{"x":0.35,"y":0},"s":[{"c":true,"i":[[0,0],[22.09,0],[0,22.09],[-22.09,0],[0,-22.09]],"o":[[0,22.09],[-22.09,0],[0,-22.09],[22.09,0],[0,0]],"v":[[80,40],[40,80],[0,40],[40,0],[80,40]]}],"t":48},{"o":{"x":0.65,"y":0},"i":{"x":0.35,"y":0},"s":[{"c":true,"i":[[0,0],[22.09,0],[0,22.09],[-22.09,0],[0,-22.09]],"o":[[0,22.09],[-22.09,0],[0,-22.09],[22.09,0],[0,0]],"v":[[80,40],[40,80],[0,40],[40,0],[80,40]]}],"t":72},{"o":{"x":0.65,"y":0},"i":{"x":0.35,"y":0},"s":[{"c":true,"i":[[0,0],[22.09,0],[0,22.09],[-22.09,0],[0,-22.09]],"o":[[0,22.09],[-22.09,0],[0,-22.09],[22.09,0],[0,0]],"v":[[80,40],[40,80],[0,40],[40,0],[80,40]]}],"t":216},{"s":[{"c":true,"i":[[0,0],[22.09,0],[0,22.09],[-22.09,0],[0,-22.09]],"o":[[0,22.09],[-22.09,0],[0,-22.09],[22.09,0],[0,0]],"v":[[80,40],[40,80],[0,40],[40,0],[80,40]]}],"t":240}]}},{"ty":"fl","bm":0,"hd":false,"nm":"","c":{"a":1,"k":[{"o":{"x":0.65,"y":0},"i":{"x":0.35,"y":0},"s":[0.7608,0.8392,0.6392],"t":0},{"o":{"x":0.65,"y":0},"i":{"x":0.35,"y":0},"s":[0.7608,0.8392,0.6392],"t":24},{"o":{"x":0.65,"y":0},"i":{"x":0.35,"y":0},"s":[0.7608,0.8392,0.6392],"t":48},{"o":{"x":0.65,"y":0},"i":{"x":0.35,"y":0},"s":[0.7608,0.8392,0.6392],"t":72},{"o":{"x":0.65,"y":0},"i":{"x":0.35,"y":0},"s":[0.7608,0.8392,0.6392],"t":216},{"s":[0.7608,0.8392,0.6392],"t":240}]},"r":1,"o":{"a":1,"k":[{"o":{"x":0.65,"y":0},"i":{"x":0.35,"y":0},"s":[100],"t":0},{"o":{"x":0.65,"y":0},"i":{"x":0.35,"y":0},"s":[100],"t":24},{"o":{"x":0.65,"y":0},"i":{"x":0.35,"y":0},"s":[100],"t":48},{"o":{"x":0.65,"y":0},"i":{"x":0.35,"y":0},"s":[100],"t":72},{"o":{"x":0.65,"y":0},"i":{"x":0.35,"y":0},"s":[100],"t":216},{"s":[100],"t":240}]}}],"ind":9},{"ty":4,"nm":"Dot 1","sr":1,"st":0,"op":241.06,"ip":0,"hd":false,"ddd":0,"bm":0,"tt":1,"hasMask":false,"ao":0,"ks":{"a":{"a":1,"k":[{"o":{"x":0.65,"y":0},"i":{"x":0.35,"y":0},"s":[2.5,2.5],"t":0},{"o":{"x":0.65,"y":0},"i":{"x":0.35,"y":0},"s":[2.5,2.5],"t":24},{"o":{"x":0.65,"y":0},"i":{"x":0.35,"y":0},"s":[2.5,2.5],"t":48},{"o":{"x":0.65,"y":0},"i":{"x":0.35,"y":0},"s":[2.5,2.5],"t":72},{"o":{"x":0.65,"y":0},"i":{"x":0.35,"y":0},"s":[2.5,2.5],"t":216},{"s":[2.5,2.5],"t":240}]},"s":{"a":1,"k":[{"o":{"x":0.65,"y":0},"i":{"x":0.35,"y":0},"s":[100,100],"t":0},{"o":{"x":0.65,"y":0},"i":{"x":0.35,"y":0},"s":[100,100],"t":24},{"o":{"x":0.65,"y":0},"i":{"x":0.35,"y":0},"s":[100,100],"t":48},{"o":{"x":0.65,"y":0},"i":{"x":0.35,"y":0},"s":[100,100],"t":72},{"o":{"x":0.65,"y":0},"i":{"x":0.35,"y":0},"s":[100,100],"t":216},{"s":[100,100],"t":240}]},"sk":{"a":0,"k":0},"p":{"a":1,"k":[{"o":{"x":0.65,"y":0},"i":{"x":0.35,"y":0},"s":[88.5,20.5],"t":0},{"o":{"x":0.65,"y":0},"i":{"x":0.35,"y":0},"s":[88.5,20.5],"t":24},{"o":{"x":0.65,"y":0},"i":{"x":0.35,"y":0},"s":[32.02,35.5],"t":48},{"o":{"x":0.65,"y":0},"i":{"x":0.35,"y":0},"s":[32.02,35.5],"t":72},{"o":{"x":0.65,"y":0},"i":{"x":0.35,"y":0},"s":[32.02,35.5],"t":216},{"s":[32.02,35.5],"t":240}]},"r":{"a":1,"k":[{"o":{"x":0.65,"y":0},"i":{"x":0.35,"y":0},"s":[0],"t":0},{"o":{"x":0.65,"y":0},"i":{"x":0.35,"y":0},"s":[0],"t":24},{"o":{"x":0.65,"y":0},"i":{"x":0.35,"y":0},"s":[0],"t":48},{"o":{"x":0.65,"y":0},"i":{"x":0.35,"y":0},"s":[0],"t":72},{"o":{"x":0.65,"y":0},"i":{"x":0.35,"y":0},"s":[0],"t":216},{"s":[0],"t":240}]},"sa":{"a":0,"k":0},"o":{"a":1,"k":[{"o":{"x":0.65,"y":0},"i":{"x":0.35,"y":0},"s":[100],"t":0},{"o":{"x":0.65,"y":0},"i":{"x":0.35,"y":0},"s":[100],"t":24},{"o":{"x":0.65,"y":0},"i":{"x":0.35,"y":0},"s":[100],"t":48},{"o":{"x":0.65,"y":0},"i":{"x":0.35,"y":0},"s":[100],"t":72},{"o":{"x":0.65,"y":0},"i":{"x":0.35,"y":0},"s":[100],"t":216},{"s":[100],"t":240}]}},"shapes":[{"ty":"sh","bm":0,"hd":false,"nm":"","d":1,"ks":{"a":1,"k":[{"o":{"x":0.65,"y":0},"i":{"x":0.35,"y":0},"s":[{"c":true,"i":[[0,0],[1.38,0],[0,1.38],[-1.38,0],[0,-1.38]],"o":[[0,1.38],[-1.38,0],[0,-1.38],[1.38,0],[0,0]],"v":[[5,2.5],[2.5,5],[0,2.5],[2.5,0],[5,2.5]]}],"t":0},{"o":{"x":0.65,"y":0},"i":{"x":0.35,"y":0},"s":[{"c":true,"i":[[0,0],[1.38,0],[0,1.38],[-1.38,0],[0,-1.38]],"o":[[0,1.38],[-1.38,0],[0,-1.38],[1.38,0],[0,0]],"v":[[5,2.5],[2.5,5],[0,2.5],[2.5,0],[5,2.5]]}],"t":24},{"o":{"x":0.65,"y":0},"i":{"x":0.35,"y":0},"s":[{"c":true,"i":[[0,0],[1.38,0],[0,1.38],[-1.38,0],[0,-1.38]],"o":[[0,1.38],[-1.38,0],[0,-1.38],[1.38,0],[0,0]],"v":[[5,2.5],[2.5,5],[0,2.5],[2.5,0],[5,2.5]]}],"t":48},{"o":{"x":0.65,"y":0},"i":{"x":0.35,"y":0},"s":[{"c":true,"i":[[0,0],[1.38,0],[0,1.38],[-1.38,0],[0,-1.38]],"o":[[0,1.38],[-1.38,0],[0,-1.38],[1.38,0],[0,0]],"v":[[5,2.5],[2.5,5],[0,2.5],[2.5,0],[5,2.5]]}],"t":72},{"o":{"x":0.65,"y":0},"i":{"x":0.35,"y":0},"s":[{"c":true,"i":[[0,0],[1.38,0],[0,1.38],[-1.38,0],[0,-1.38]],"o":[[0,1.38],[-1.38,0],[0,-1.38],[1.38,0],[0,0]],"v":[[5,2.5],[2.5,5],[0,2.5],[2.5,0],[5,2.5]]}],"t":216},{"s":[{"c":true,"i":[[0,0],[1.38,0],[0,1.38],[-1.38,0],[0,-1.38]],"o":[[0,1.38],[-1.38,0],[0,-1.38],[1.38,0],[0,0]],"v":[[5,2.5],[2.5,5],[0,2.5],[2.5,0],[5,2.5]]}],"t":240}]}},{"ty":"fl","bm":0,"hd":false,"nm":"","c":{"a":1,"k":[{"o":{"x":0.65,"y":0},"i":{"x":0.35,"y":0},"s":[0,0.3294,0.3137],"t":0},{"o":{"x":0.65,"y":0},"i":{"x":0.35,"y":0},"s":[0,0.3294,0.3137],"t":24},{"o":{"x":0.65,"y":0},"i":{"x":0.35,"y":0},"s":[0,0.3294,0.3137],"t":48},{"o":{"x":0.65,"y":0},"i":{"x":0.35,"y":0},"s":[0,0.3294,0.3137],"t":72},{"o":{"x":0.65,"y":0},"i":{"x":0.35,"y":0},"s":[0,0.3294,0.3137],"t":216},{"s":[0,0.3294,0.3137],"t":240}]},"r":1,"o":{"a":1,"k":[{"o":{"x":0.65,"y":0},"i":{"x":0.35,"y":0},"s":[100],"t":0},{"o":{"x":0.65,"y":0},"i":{"x":0.35,"y":0},"s":[100],"t":24},{"o":{"x":0.65,"y":0},"i":{"x":0.35,"y":0},"s":[100],"t":48},{"o":{"x":0.65,"y":0},"i":{"x":0.35,"y":0},"s":[100],"t":72},{"o":{"x":0.65,"y":0},"i":{"x":0.35,"y":0},"s":[100],"t":216},{"s":[100],"t":240}]}}],"ind":10},{"ty":4,"nm":"Ellipse 1","sr":1,"st":0,"op":241.06,"ip":0,"hd":false,"ddd":0,"bm":0,"hasMask":false,"td":1,"ao":0,"ks":{"a":{"a":1,"k":[{"o":{"x":0.65,"y":0},"i":{"x":0.35,"y":0},"s":[40,40],"t":0},{"o":{"x":0.65,"y":0},"i":{"x":0.35,"y":0},"s":[40,40],"t":24},{"o":{"x":0.65,"y":0},"i":{"x":0.35,"y":0},"s":[40,40],"t":48},{"o":{"x":0.65,"y":0},"i":{"x":0.35,"y":0},"s":[40,40],"t":72},{"o":{"x":0.65,"y":0},"i":{"x":0.35,"y":0},"s":[40,40],"t":216},{"s":[40,40],"t":240}]},"s":{"a":1,"k":[{"o":{"x":0.65,"y":0},"i":{"x":0.35,"y":0},"s":[100,100],"t":0},{"o":{"x":0.65,"y":0},"i":{"x":0.35,"y":0},"s":[100,100],"t":24},{"o":{"x":0.65,"y":0},"i":{"x":0.35,"y":0},"s":[100,100],"t":48},{"o":{"x":0.65,"y":0},"i":{"x":0.35,"y":0},"s":[100,100],"t":72},{"o":{"x":0.65,"y":0},"i":{"x":0.35,"y":0},"s":[100,100],"t":216},{"s":[100,100],"t":240}]},"sk":{"a":0,"k":0},"p":{"a":1,"k":[{"o":{"x":0.65,"y":0},"i":{"x":0.35,"y":0},"s":[40,40],"t":0},{"o":{"x":0.65,"y":0},"i":{"x":0.35,"y":0},"s":[40,40],"t":24},{"o":{"x":0.65,"y":0},"i":{"x":0.35,"y":0},"s":[40,40],"t":48},{"o":{"x":0.65,"y":0},"i":{"x":0.35,"y":0},"s":[40,40],"t":72},{"o":{"x":0.65,"y":0},"i":{"x":0.35,"y":0},"s":[40,40],"t":216},{"s":[40,40],"t":240}]},"r":{"a":1,"k":[{"o":{"x":0.65,"y":0},"i":{"x":0.35,"y":0},"s":[0],"t":0},{"o":{"x":0.65,"y":0},"i":{"x":0.35,"y":0},"s":[0],"t":24},{"o":{"x":0.65,"y":0},"i":{"x":0.35,"y":0},"s":[0],"t":48},{"o":{"x":0.65,"y":0},"i":{"x":0.35,"y":0},"s":[0],"t":72},{"o":{"x":0.65,"y":0},"i":{"x":0.35,"y":0},"s":[0],"t":216},{"s":[0],"t":240}]},"sa":{"a":0,"k":0},"o":{"a":1,"k":[{"o":{"x":0.65,"y":0},"i":{"x":0.35,"y":0},"s":[100],"t":0},{"o":{"x":0.65,"y":0},"i":{"x":0.35,"y":0},"s":[100],"t":24},{"o":{"x":0.65,"y":0},"i":{"x":0.35,"y":0},"s":[100],"t":48},{"o":{"x":0.65,"y":0},"i":{"x":0.35,"y":0},"s":[100],"t":72},{"o":{"x":0.65,"y":0},"i":{"x":0.35,"y":0},"s":[100],"t":216},{"s":[100],"t":240}]}},"shapes":[{"ty":"sh","bm":0,"hd":false,"nm":"","d":1,"ks":{"a":1,"k":[{"o":{"x":0.65,"y":0},"i":{"x":0.35,"y":0},"s":[{"c":true,"i":[[0,0],[22.09,0],[0,22.09],[-22.09,0],[0,-22.09]],"o":[[0,22.09],[-22.09,0],[0,-22.09],[22.09,0],[0,0]],"v":[[80,40],[40,80],[0,40],[40,0],[80,40]]}],"t":0},{"o":{"x":0.65,"y":0},"i":{"x":0.35,"y":0},"s":[{"c":true,"i":[[0,0],[22.09,0],[0,22.09],[-22.09,0],[0,-22.09]],"o":[[0,22.09],[-22.09,0],[0,-22.09],[22.09,0],[0,0]],"v":[[80,40],[40,80],[0,40],[40,0],[80,40]]}],"t":24},{"o":{"x":0.65,"y":0},"i":{"x":0.35,"y":0},"s":[{"c":true,"i":[[0,0],[22.09,0],[0,22.09],[-22.09,0],[0,-22.09]],"o":[[0,22.09],[-22.09,0],[0,-22.09],[22.09,0],[0,0]],"v":[[80,40],[40,80],[0,40],[40,0],[80,40]]}],"t":48},{"o":{"x":0.65,"y":0},"i":{"x":0.35,"y":0},"s":[{"c":true,"i":[[0,0],[22.09,0],[0,22.09],[-22.09,0],[0,-22.09]],"o":[[0,22.09],[-22.09,0],[0,-22.09],[22.09,0],[0,0]],"v":[[80,40],[40,80],[0,40],[40,0],[80,40]]}],"t":72},{"o":{"x":0.65,"y":0},"i":{"x":0.35,"y":0},"s":[{"c":true,"i":[[0,0],[22.09,0],[0,22.09],[-22.09,0],[0,-22.09]],"o":[[0,22.09],[-22.09,0],[0,-22.09],[22.09,0],[0,0]],"v":[[80,40],[40,80],[0,40],[40,0],[80,40]]}],"t":216},{"s":[{"c":true,"i":[[0,0],[22.09,0],[0,22.09],[-22.09,0],[0,-22.09]],"o":[[0,22.09],[-22.09,0],[0,-22.09],[22.09,0],[0,0]],"v":[[80,40],[40,80],[0,40],[40,0],[80,40]]}],"t":240}]}},{"ty":"fl","bm":0,"hd":false,"nm":"","c":{"a":1,"k":[{"o":{"x":0.65,"y":0},"i":{"x":0.35,"y":0},"s":[0.7608,0.8392,0.6392],"t":0},{"o":{"x":0.65,"y":0},"i":{"x":0.35,"y":0},"s":[0.7608,0.8392,0.6392],"t":24},{"o":{"x":0.65,"y":0},"i":{"x":0.35,"y":0},"s":[0.7608,0.8392,0.6392],"t":48},{"o":{"x":0.65,"y":0},"i":{"x":0.35,"y":0},"s":[0.7608,0.8392,0.6392],"t":72},{"o":{"x":0.65,"y":0},"i":{"x":0.35,"y":0},"s":[0.7608,0.8392,0.6392],"t":216},{"s":[0.7608,0.8392,0.6392],"t":240}]},"r":1,"o":{"a":1,"k":[{"o":{"x":0.65,"y":0},"i":{"x":0.35,"y":0},"s":[100],"t":0},{"o":{"x":0.65,"y":0},"i":{"x":0.35,"y":0},"s":[100],"t":24},{"o":{"x":0.65,"y":0},"i":{"x":0.35,"y":0},"s":[100],"t":48},{"o":{"x":0.65,"y":0},"i":{"x":0.35,"y":0},"s":[100],"t":72},{"o":{"x":0.65,"y":0},"i":{"x":0.35,"y":0},"s":[100],"t":216},{"s":[100],"t":240}]}}],"ind":11},{"ty":4,"nm":"Board","sr":1,"st":0,"op":241.06,"ip":0,"hd":false,"ddd":0,"bm":0,"tt":1,"hasMask":false,"ao":0,"ks":{"a":{"a":1,"k":[{"o":{"x":0.65,"y":0},"i":{"x":0.35,"y":0},"s":[8.57,4.76],"t":0},{"o":{"x":0.65,"y":0},"i":{"x":0.35,"y":0},"s":[8.57,4.76],"t":24},{"o":{"x":0.65,"y":0},"i":{"x":0.35,"y":0},"s":[17,16],"t":48},{"o":{"x":0.65,"y":0},"i":{"x":0.35,"y":0},"s":[17.14,20.95],"t":72},{"o":{"x":0.65,"y":0},"i":{"x":0.35,"y":0},"s":[17.14,20.95],"t":216},{"s":[17.14,20.95],"t":240}]},"s":{"a":1,"k":[{"o":{"x":0.65,"y":0},"i":{"x":0.35,"y":0},"s":[100,100],"t":0},{"o":{"x":0.65,"y":0},"i":{"x":0.35,"y":0},"s":[100,100],"t":24},{"o":{"x":0.65,"y":0},"i":{"x":0.35,"y":0},"s":[100,100],"t":48},{"o":{"x":0.65,"y":0},"i":{"x":0.35,"y":0},"s":[100,100],"t":72},{"o":{"x":0.65,"y":0},"i":{"x":0.35,"y":0},"s":[100,100],"t":216},{"s":[100,100],"t":240}]},"sk":{"a":0,"k":0},"p":{"a":1,"k":[{"o":{"x":0.65,"y":0},"i":{"x":0.35,"y":0},"s":[89.32,21.51],"t":0},{"o":{"x":0.65,"y":0},"i":{"x":0.35,"y":0},"s":[89.32,21.51],"t":24},{"o":{"x":0.65,"y":0},"i":{"x":0.35,"y":0},"s":[40.75,35.75],"t":48},{"o":{"x":0.65,"y":0},"i":{"x":0.35,"y":0},"s":[40.75,40.7],"t":72},{"o":{"x":0.65,"y":0},"i":{"x":0.35,"y":0},"s":[40.75,40.7],"t":216},{"s":[40.75,40.75],"t":240}]},"r":{"a":1,"k":[{"o":{"x":0.65,"y":0},"i":{"x":0.35,"y":0},"s":[0],"t":0},{"o":{"x":0.65,"y":0},"i":{"x":0.35,"y":0},"s":[0],"t":24},{"o":{"x":0.65,"y":0},"i":{"x":0.35,"y":0},"s":[0],"t":48},{"o":{"x":0.65,"y":0},"i":{"x":0.35,"y":0},"s":[0],"t":72},{"o":{"x":0.65,"y":0},"i":{"x":0.35,"y":0},"s":[0],"t":216},{"s":[0],"t":240}]},"sa":{"a":0,"k":0},"o":{"a":1,"k":[{"o":{"x":0.65,"y":0},"i":{"x":0.35,"y":0},"s":[100],"t":0},{"o":{"x":0.65,"y":0},"i":{"x":0.35,"y":0},"s":[100],"t":24},{"o":{"x":0.65,"y":0},"i":{"x":0.35,"y":0},"s":[100],"t":48},{"o":{"x":0.65,"y":0},"i":{"x":0.35,"y":0},"s":[100],"t":72},{"o":{"x":0.65,"y":0},"i":{"x":0.35,"y":0},"s":[100],"t":216},{"s":[100],"t":240}]}},"shapes":[{"ty":"sh","bm":0,"hd":false,"nm":"","d":1,"ks":{"a":1,"k":[{"o":{"x":0.65,"y":0},"i":{"x":0.35,"y":0},"s":[{"c":true,"i":[[0,0],[-0.5748658090051786,0],[0,0],[0,-0.5307352988907326],[0,0],[0.5748658090051786,0],[0,0],[0,0.5307352988907326],[0,0]],"o":[[0,-0.5307352988907326],[0,0],[0.5748658090051786,0],[0,0],[0,0.5307352988907326],[0,0],[-0.5748658090051786,0],[0,0],[0,0]],"v":[[0,0.9603781598975161],[1.0402333686760372,0],[14.599766577909296,0],[15.639999946585334,0.9603781598975161],[15.639999946585334,7.05962191222911],[14.599766577909296,8.020000072126626],[1.0402333686760372,8.020000072126626],[0,7.05962191222911],[0,0.9603781598975161]]}],"t":0},{"o":{"x":0.65,"y":0},"i":{"x":0.35,"y":0},"s":[{"c":true,"i":[[0,0],[-0.5748658090051786,0],[0,0],[0,-0.5307352988907326],[0,0],[0.5748658090051786,0],[0,0],[0,0.5307352988907326],[0,0]],"o":[[0,-0.5307352988907326],[0,0],[0.5748658090051786,0],[0,0],[0,0.5307352988907326],[0,0],[-0.5748658090051786,0],[0,0],[0,0]],"v":[[0,0.9603781598975161],[1.0402333686760372,0],[14.599766577909296,0],[15.639999946585334,0.9603781598975161],[15.639999946585334,7.05962191222911],[14.599766577909296,8.020000072126626],[1.0402333686760372,8.020000072126626],[0,7.05962191222911],[0,0.9603781598975161]]}],"t":24},{"o":{"x":0.65,"y":0},"i":{"x":0.35,"y":0},"s":[{"c":true,"i":[[0,0],[-1.0514705882352942,0],[0,0],[0,-1.0484375000000001],[0,0],[2.408823529411765,0],[0,0],[0,2.401875],[0,0]],"o":[[0,-1.0484375000000001],[0,0],[1.0514705882352942,0],[0,0],[0,2.401875],[0,0],[-2.408823529411765,0],[0,0],[0,0]],"v":[[0,1.90625],[1.911764705882353,0],[30.58823529411765,0],[32.5,1.90625],[32.5,26.14421875],[28.131617647058825,30.5],[4.368382352941177,30.5],[0,26.14421875],[0,1.90625]]}],"t":48},{"o":{"x":0.65,"y":0},"i":{"x":0.35,"y":0},"s":[{"c":true,"i":[[0,0],[-1.0518749984701474,0],[0,0],[0,-1.0606250003413722],[0,0],[2.409749996495247,0],[0,0],[0,2.4297954553275067],[0,0]],"o":[[0,-1.0606250003413722],[0,0],[1.0518749984701474,0],[0,0],[0,2.4297954553275067],[0,0],[-2.409749996495247,0],[0,0],[0,0]],"v":[[0,1.9284090915297674],[1.9124999972184498,0],[30.87731245509187,0],[32.78981245231032,1.9284090915297674],[32.78981245231032,35.99375569340311],[28.41018745868007,40.40017046754863],[4.370062493644158,40.40017046754863],[0,35.99375569340311],[0,1.9284090915297674]]}],"t":72},{"o":{"x":0.65,"y":0},"i":{"x":0.35,"y":0},"s":[{"c":true,"i":[[0,0],[-1.0518749984701474,0],[0,0],[0,-1.0606250003413722],[0,0],[2.409749996495247,0],[0,0],[0,2.4297954553275067],[0,0]],"o":[[0,-1.0606250003413722],[0,0],[1.0518749984701474,0],[0,0],[0,2.4297954553275067],[0,0],[-2.409749996495247,0],[0,0],[0,0]],"v":[[0,1.9284090915297674],[1.9124999972184498,0],[30.87731245509187,0],[32.78981245231032,1.9284090915297674],[32.78981245231032,35.99375569340311],[28.41018745868007,40.40017046754863],[4.370062493644158,40.40017046754863],[0,35.99375569340311],[0,1.9284090915297674]]}],"t":216},{"s":[{"c":true,"i":[[0,0],[-1.0518749984701474,0],[0,0],[0,-1.0606250003413722],[0,0],[2.409749996495247,0],[0,0],[0,2.4297954553275067],[0,0]],"o":[[0,-1.0606250003413722],[0,0],[1.0518749984701474,0],[0,0],[0,2.4297954553275067],[0,0],[-2.409749996495247,0],[0,0],[0,0]],"v":[[0,1.9284090915297674],[1.9124999972184498,0],[30.87731245509187,0],[32.78981245231032,1.9284090915297674],[32.78981245231032,35.99375569340311],[28.41018745868007,40.40017046754863],[4.370062493644158,40.40017046754863],[0,35.99375569340311],[0,1.9284090915297674]]}],"t":240}]}},{"ty":"st","bm":0,"hd":false,"nm":"","lc":1,"lj":1,"ml":4,"o":{"a":1,"k":[{"o":{"x":0.65,"y":0},"i":{"x":0.35,"y":0},"s":[100],"t":0},{"o":{"x":0.65,"y":0},"i":{"x":0.35,"y":0},"s":[100],"t":24},{"o":{"x":0.65,"y":0},"i":{"x":0.35,"y":0},"s":[100],"t":48},{"o":{"x":0.65,"y":0},"i":{"x":0.35,"y":0},"s":[100],"t":72},{"o":{"x":0.65,"y":0},"i":{"x":0.35,"y":0},"s":[100],"t":216},{"s":[100],"t":240}]},"w":{"a":1,"k":[{"o":{"x":0.65,"y":0},"i":{"x":0.35,"y":0},"s":[1.5],"t":0},{"o":{"x":0.65,"y":0},"i":{"x":0.35,"y":0},"s":[1.5],"t":24},{"o":{"x":0.65,"y":0},"i":{"x":0.35,"y":0},"s":[1.5],"t":48},{"o":{"x":0.65,"y":0},"i":{"x":0.35,"y":0},"s":[1.5],"t":72},{"o":{"x":0.65,"y":0},"i":{"x":0.35,"y":0},"s":[1.5],"t":216},{"s":[1.5],"t":240}]},"c":{"a":1,"k":[{"o":{"x":0.65,"y":0},"i":{"x":0.35,"y":0},"s":[0,0.3294,0.3137],"t":0},{"o":{"x":0.65,"y":0},"i":{"x":0.35,"y":0},"s":[0,0.3294,0.3137],"t":24},{"o":{"x":0.65,"y":0},"i":{"x":0.35,"y":0},"s":[0,0.3294,0.3137],"t":48},{"o":{"x":0.65,"y":0},"i":{"x":0.35,"y":0},"s":[0,0.3294,0.3137],"t":72},{"o":{"x":0.65,"y":0},"i":{"x":0.35,"y":0},"s":[0,0.3294,0.3137],"t":216},{"s":[0,0.3294,0.3137],"t":240}]}},{"ty":"fl","bm":0,"hd":false,"nm":"","c":{"a":1,"k":[{"o":{"x":0.65,"y":0},"i":{"x":0.35,"y":0},"s":[1,1,1],"t":0},{"o":{"x":0.65,"y":0},"i":{"x":0.35,"y":0},"s":[1,1,1],"t":24},{"o":{"x":0.65,"y":0},"i":{"x":0.35,"y":0},"s":[1,1,1],"t":48},{"o":{"x":0.65,"y":0},"i":{"x":0.35,"y":0},"s":[1,1,1],"t":72},{"o":{"x":0.65,"y":0},"i":{"x":0.35,"y":0},"s":[1,1,1],"t":216},{"s":[1,1,1],"t":240}]},"r":1,"o":{"a":1,"k":[{"o":{"x":0.65,"y":0},"i":{"x":0.35,"y":0},"s":[100],"t":0},{"o":{"x":0.65,"y":0},"i":{"x":0.35,"y":0},"s":[100],"t":24},{"o":{"x":0.65,"y":0},"i":{"x":0.35,"y":0},"s":[100],"t":48},{"o":{"x":0.65,"y":0},"i":{"x":0.35,"y":0},"s":[100],"t":72},{"o":{"x":0.65,"y":0},"i":{"x":0.35,"y":0},"s":[100],"t":216},{"s":[100],"t":240}]}}],"ind":12},{"ty":4,"nm":"Green","sr":1,"st":0,"op":241.06,"ip":0,"hd":false,"ddd":0,"bm":0,"hasMask":false,"ao":0,"ks":{"a":{"a":1,"k":[{"o":{"x":0.65,"y":0},"i":{"x":0.35,"y":0},"s":[0.5,0.5],"t":0},{"o":{"x":0.65,"y":0},"i":{"x":0.35,"y":0},"s":[0.5,0.5],"t":24},{"o":{"x":0.65,"y":0},"i":{"x":0.35,"y":0},"s":[40,40],"t":48},{"o":{"x":0.65,"y":0},"i":{"x":0.35,"y":0},"s":[40,40],"t":72},{"o":{"x":0.65,"y":0},"i":{"x":0.35,"y":0},"s":[40,40],"t":216},{"s":[40,40],"t":240}]},"s":{"a":1,"k":[{"o":{"x":0.65,"y":0},"i":{"x":0.35,"y":0},"s":[100,100],"t":0},{"o":{"x":0.65,"y":0},"i":{"x":0.35,"y":0},"s":[100,100],"t":24},{"o":{"x":0.65,"y":0},"i":{"x":0.35,"y":0},"s":[100,100],"t":48},{"o":{"x":0.65,"y":0},"i":{"x":0.35,"y":0},"s":[100,100],"t":72},{"o":{"x":0.65,"y":0},"i":{"x":0.35,"y":0},"s":[100,100],"t":216},{"s":[100,100],"t":240}]},"sk":{"a":0,"k":0},"p":{"a":1,"k":[{"o":{"x":0.65,"y":0},"i":{"x":0.35,"y":0},"s":[39.5,40.5],"t":0},{"o":{"x":0.65,"y":0},"i":{"x":0.35,"y":0},"s":[39.5,40.5],"t":24},{"o":{"x":0.65,"y":0},"i":{"x":0.35,"y":0},"s":[40,40],"t":48},{"o":{"x":0.65,"y":0},"i":{"x":0.35,"y":0},"s":[40,40],"t":72},{"o":{"x":0.65,"y":0},"i":{"x":0.35,"y":0},"s":[40,40],"t":216},{"s":[40,40],"t":240}]},"r":{"a":1,"k":[{"o":{"x":0.65,"y":0},"i":{"x":0.35,"y":0},"s":[0],"t":0},{"o":{"x":0.65,"y":0},"i":{"x":0.35,"y":0},"s":[0],"t":24},{"o":{"x":0.65,"y":0},"i":{"x":0.35,"y":0},"s":[0],"t":48},{"o":{"x":0.65,"y":0},"i":{"x":0.35,"y":0},"s":[0],"t":72},{"o":{"x":0.65,"y":0},"i":{"x":0.35,"y":0},"s":[0],"t":216},{"s":[0],"t":240}]},"sa":{"a":0,"k":0},"o":{"a":1,"k":[{"o":{"x":0.65,"y":0},"i":{"x":0.35,"y":0},"s":[100],"t":0},{"o":{"x":0.65,"y":0},"i":{"x":0.35,"y":0},"s":[100],"t":24},{"o":{"x":0.65,"y":0},"i":{"x":0.35,"y":0},"s":[100],"t":48},{"o":{"x":0.65,"y":0},"i":{"x":0.35,"y":0},"s":[100],"t":72},{"o":{"x":0.65,"y":0},"i":{"x":0.35,"y":0},"s":[100],"t":216},{"s":[100],"t":240}]}},"shapes":[{"ty":"sh","bm":0,"hd":false,"nm":"","d":1,"ks":{"a":1,"k":[{"o":{"x":0.65,"y":0},"i":{"x":0.35,"y":0},"s":[{"c":true,"i":[[0,0],[0.28,0],[0,0.28],[-0.28,0],[0,-0.28]],"o":[[0,0.28],[-0.28,0],[0,-0.28],[0.28,0],[0,0]],"v":[[1,0.5],[0.5,1],[0,0.5],[0.5,0],[1,0.5]]}],"t":0},{"o":{"x":0.65,"y":0},"i":{"x":0.35,"y":0},"s":[{"c":true,"i":[[0,0],[0.28,0],[0,0.28],[-0.28,0],[0,-0.28]],"o":[[0,0.28],[-0.28,0],[0,-0.28],[0.28,0],[0,0]],"v":[[1,0.5],[0.5,1],[0,0.5],[0.5,0],[1,0.5]]}],"t":24},{"o":{"x":0.65,"y":0},"i":{"x":0.35,"y":0},"s":[{"c":true,"i":[[0,0],[22.09,0],[0,22.09],[-22.09,0],[0,-22.09]],"o":[[0,22.09],[-22.09,0],[0,-22.09],[22.09,0],[0,0]],"v":[[80,40],[40,80],[0,40],[40,0],[80,40]]}],"t":48},{"o":{"x":0.65,"y":0},"i":{"x":0.35,"y":0},"s":[{"c":true,"i":[[0,0],[22.09,0],[0,22.09],[-22.09,0],[0,-22.09]],"o":[[0,22.09],[-22.09,0],[0,-22.09],[22.09,0],[0,0]],"v":[[80,40],[40,80],[0,40],[40,0],[80,40]]}],"t":72},{"o":{"x":0.65,"y":0},"i":{"x":0.35,"y":0},"s":[{"c":true,"i":[[0,0],[22.09,0],[0,22.09],[-22.09,0],[0,-22.09]],"o":[[0,22.09],[-22.09,0],[0,-22.09],[22.09,0],[0,0]],"v":[[80,40],[40,80],[0,40],[40,0],[80,40]]}],"t":216},{"s":[{"c":true,"i":[[0,0],[22.09,0],[0,22.09],[-22.09,0],[0,-22.09]],"o":[[0,22.09],[-22.09,0],[0,-22.09],[22.09,0],[0,0]],"v":[[80,40],[40,80],[0,40],[40,0],[80,40]]}],"t":240}]}},{"ty":"fl","bm":0,"hd":false,"nm":"","c":{"a":1,"k":[{"o":{"x":0.65,"y":0},"i":{"x":0.35,"y":0},"s":[0.7608,0.8392,0.6392],"t":0},{"o":{"x":0.65,"y":0},"i":{"x":0.35,"y":0},"s":[0.7608,0.8392,0.6392],"t":24},{"o":{"x":0.65,"y":0},"i":{"x":0.35,"y":0},"s":[0.7608,0.8392,0.6392],"t":48},{"o":{"x":0.65,"y":0},"i":{"x":0.35,"y":0},"s":[0.7608,0.8392,0.6392],"t":72},{"o":{"x":0.65,"y":0},"i":{"x":0.35,"y":0},"s":[0.7608,0.8392,0.6392],"t":216},{"s":[0.7608,0.8392,0.6392],"t":240}]},"r":1,"o":{"a":1,"k":[{"o":{"x":0.65,"y":0},"i":{"x":0.35,"y":0},"s":[100],"t":0},{"o":{"x":0.65,"y":0},"i":{"x":0.35,"y":0},"s":[100],"t":24},{"o":{"x":0.65,"y":0},"i":{"x":0.35,"y":0},"s":[100],"t":48},{"o":{"x":0.65,"y":0},"i":{"x":0.35,"y":0},"s":[100],"t":72},{"o":{"x":0.65,"y":0},"i":{"x":0.35,"y":0},"s":[100],"t":216},{"s":[100],"t":240}]}}],"ind":13}],"v":"5.7.0","fr":60,"op":240.06,"ip":0,"assets":[]}